[
  {
    "title": "Lead ML Scientist , Adobe",
    "name": "Amine Ben khalifa",
    "username": "@aminert",
    "interests": ["Beta testing new products", "Raising funding", "Advising companies"],
    "img": "https://polywork-production.imgix.net/1fcz8vofqlwmoly9xxrrv8sbtnxa?ixlib=rails-4.2.0&url_params=%7B%3Aw%3D%3E128%2C%20%3Ah%3D%3E128%2C%20%3Afit%3D%3E%22crop%22%2C%20%3Aauto%3D%3E%22format%22%7D"
  },
  {
    "title": "Strategy and research, Arcadia",
    "name": "Christopher Monnier",
    "username": "@chrismonnier",
    "interests": ["Guest lecturing", "Speaking on Clubhouse", "Mentoring"],
    "img": "https://polywork-production.imgix.net/d8jdw48ujzs0t4n56xrg16td331h?ixlib=rails-4.2.0&url_params=%7B%3Aw%3D%3E128%2C%20%3Ah%3D%3E128%2C%20%3Afit%3D%3E%22crop%22%2C%20%3Aauto%3D%3E%22format%22%7D"
  },
  {
    "title": "Senior Software Engineer, Airbnb",
    "name": "Chris Lindsey",
    "username": "@clindsey",
    "interests": ["Partnering on Side Projects", "Full time roles", "Brainstorming"],
    "img": "https://polywork-production.imgix.net/vnan3exjowgqgz7wtwiayb897thy?ixlib=rails-4.2.0&url_params=%7B%3Aw%3D%3E128%2C%20%3Ah%3D%3E128%2C%20%3Afit%3D%3E%22crop%22%2C%20%3Aauto%3D%3E%22format%22%7D"
  },
  {
    "title": "Staff Designer, GitHub",
    "name": "Adrian Mato",
    "username": "@adrian",
    "interests": ["Full time roles", "Advising companies", "Speaking at Events"],
    "img": "https://polywork-production.imgix.net/arle8j65v0nehox8fz7oryjox8rp?ixlib=rails-4.2.0&url_params=%7B%3Aw%3D%3E128%2C%20%3Ah%3D%3E128%2C%20%3Afit%3D%3E%22crop%22%2C%20%3Aauto%3D%3E%22format%22%7D"
  },
  {
    "title": "Product Designer, Square",
    "name": "Haley Park",
    "username": "@haleysdesign",
    "interests": ["Partnering on Side Projects", "Giving resume feedback", "Guest lecturing"],
    "img": "https://polywork-production.imgix.net/fr3hn77penxlc69kr0n65k0zsigt?ixlib=rails-4.2.0&url_params=%7B%3Aw%3D%3E128%2C%20%3Ah%3D%3E128%2C%20%3Afit%3D%3E%22crop%22%2C%20%3Aauto%3D%3E%22format%22%7D"
  },
  {
    "title": "Software Engineer, Uber Eats",
    "name": "faraz ahmad",
    "username": "@faraz",
    "interests": ["Writing"],
    "img": "https://polywork-production.imgix.net/217ukq05qh9zkc9nn5s5bt5l62s3?ixlib=rails-4.2.0&url_params=%7B%3Aw%3D%3E128%2C%20%3Ah%3D%3E128%2C%20%3Afit%3D%3E%22crop%22%2C%20%3Aauto%3D%3E%22format%22%7D"
  },
  {
    "title": "Product Designer, Instagram",
    "name": "Jude Sue",
    "username": "@judesue",
    "interests": ["Partnering on Side Projects", "Raising funding", "Investing"],
    "img": "https://polywork-production.imgix.net/s16j728mxcv6k6mn166ypixl0j0j?ixlib=rails-4.2.0&url_params=%7B%3Aw%3D%3E128%2C%20%3Ah%3D%3E128%2C%20%3Afit%3D%3E%22crop%22%2C%20%3Aauto%3D%3E%22format%22%7D"
  },
  {
    "title": "Partner, SciFi",
    "name": "Alex Hartz\n\n\n",
    "username": "@alex",
    "interests": ["Advising companies", "Mentoring", "Speaking at Events"],
    "img": "https://polywork-production.imgix.net/ejbyk82y2zm2qx7cqc6ftdy9ba2f?ixlib=rails-4.2.0&url_params=%7B%3Aw%3D%3E128%2C%20%3Ah%3D%3E128%2C%20%3Afit%3D%3E%22crop%22%2C%20%3Aauto%3D%3E%22format%22%7D"
  },
  {
    "title": "Senior Software Engineer, Apple Inc",
    "name": "David Ohayon",
    "username": "@ohayon",
    "interests": ["Investing", "Activism", "Mentoring"],
    "img": ""
  },
  {
    "title": "Product Designer , Pinterest",
    "name": "Edgar Chaparro",
    "username": "@esteelo",
    "interests": ["Speaking on Clubhouse", "Speaking at Events", "Guest lecturing"],
    "img": "https://polywork-production.imgix.net/7g22g67xfvoranmoimbw4dinw6wm?ixlib=rails-4.2.0&url_params=%7B%3Aw%3D%3E128%2C%20%3Ah%3D%3E128%2C%20%3Afit%3D%3E%22crop%22%2C%20%3Aauto%3D%3E%22format%22%7D"
  },
  {
    "title": "Designer, Slack",
    "name": "William Miner",
    "username": "@wgminer",
    "interests": ["Investing", "Guest lecturing"],
    "img": "https://polywork-production.imgix.net/sfczi7e21prbrscw0h261ntxcttu?ixlib=rails-4.2.0&url_params=%7B%3Aw%3D%3E128%2C%20%3Ah%3D%3E128%2C%20%3Afit%3D%3E%22crop%22%2C%20%3Aauto%3D%3E%22format%22%7D"
  },
  {
    "title": "CEO, Discord",
    "name": "Jason Citron",
    "username": "@jasoncitron",
    "interests": ["Mentoring", "Advising companies"],
    "img": "https://polywork-production.imgix.net/mhca47zq7ua3t5o5pxoxmvrozaju?ixlib=rails-4.2.0&url_params=%7B%3Aw%3D%3E128%2C%20%3Ah%3D%3E128%2C%20%3Afit%3D%3E%22crop%22%2C%20%3Aauto%3D%3E%22format%22%7D"
  },
  {
    "title": "Software Engineer, Stripe",
    "name": "Emma Segal-Grossman",
    "username": "@esg",
    "interests": ["Participating in User Research", "Making Introductions", "Beta testing new products"],
    "img": "https://polywork-production.imgix.net/1zd2w7exam5pz6n60snvss0m7fed?ixlib=rails-4.2.0&url_params=%7B%3Aw%3D%3E128%2C%20%3Ah%3D%3E128%2C%20%3Afit%3D%3E%22crop%22%2C%20%3Aauto%3D%3E%22format%22%7D"
  },
  {
    "title": "Supply Lead, Airbnb",
    "name": "Alvan Aiau Yong",
    "username": "@alvanaiauyong",
    "interests": ["Beta testing new products", "Brainstorming", "Speaking at Events"],
    "img": "https://polywork-production.imgix.net/idizi1u2k6kqp8iohcqiazo8hxov?ixlib=rails-4.2.0&url_params=%7B%3Aw%3D%3E128%2C%20%3Ah%3D%3E128%2C%20%3Afit%3D%3E%22crop%22%2C%20%3Aauto%3D%3E%22format%22%7D"
  },
  {
    "title": "Software Engineer, Stripe",
    "name": "Kevin Peters",
    "username": "@kevinpeters",
    "interests": ["Open Source Contributions", "Investing", "Giving resume feedback"],
    "img": "https://polywork-production.imgix.net/wva2vpojy3p9r69dfdpp34jqkwmn?ixlib=rails-4.2.0&url_params=%7B%3Aw%3D%3E128%2C%20%3Ah%3D%3E128%2C%20%3Afit%3D%3E%22crop%22%2C%20%3Aauto%3D%3E%22format%22%7D"
  },
  {
    "title": "Software Engineer in Test , Spotify",
    "name": "Laura Egar",
    "username": "@lauraegar",
    "interests": ["Full time roles", "Open Source Contributions", "Writing"],
    "img": "https://polywork-production.imgix.net/8doz4b02fp6uu7apb9aem6cko1z4?ixlib=rails-4.2.0&url_params=%7B%3Aw%3D%3E128%2C%20%3Ah%3D%3E128%2C%20%3Afit%3D%3E%22crop%22%2C%20%3Aauto%3D%3E%22format%22%7D"
  },
  {
    "title": "Principal UX Designer, Twitch",
    "name": "John Ellenich",
    "username": "@ellenich",
    "interests": ["Live Streaming", "Partnering on Side Projects"],
    "img": "https://polywork-production.imgix.net/ngjvsviwr3fv6t4djqllusi9q2c7?ixlib=rails-4.2.0&url_params=%7B%3Aw%3D%3E128%2C%20%3Ah%3D%3E128%2C%20%3Afit%3D%3E%22crop%22%2C%20%3Aauto%3D%3E%22format%22%7D"
  },
  {
    "title": "Founder, Kearny Jackson",
    "name": "Sriram Krishnan\n\n\n",
    "username": "@sriram",
    "interests": ["Investing", "Speaking at Events", "Advising companies"],
    "img": "https://polywork-production.imgix.net/hezbljxcaq65xzcijpkxqxd3ahva?ixlib=rails-4.2.0&url_params=%7B%3Aw%3D%3E128%2C%20%3Ah%3D%3E128%2C%20%3Afit%3D%3E%22crop%22%2C%20%3Aauto%3D%3E%22format%22%7D"
  },
  {
    "title": "Founder, Managing Partner, Caffeinated Capital",
    "name": "Raymond Tonsing\n\n\n",
    "username": "@tonsing",
    "interests": ["Investing", "Raising funding", "Beta testing new products"],
    "img": "https://polywork-production.imgix.net/xxvj67jiovv12jquc1n4kwe8miep?ixlib=rails-4.2.0&url_params=%7B%3Aw%3D%3E128%2C%20%3Ah%3D%3E128%2C%20%3Afit%3D%3E%22crop%22%2C%20%3Aauto%3D%3E%22format%22%7D"
  },
  {
    "title": "Software Engineer, The New York Times",
    "name": "Nick Foden",
    "username": "@nickfoden",
    "interests": ["Activism", "Advising companies", "Beta testing new products"],
    "img": "https://polywork-production.imgix.net/o4i76zcbve687zzyuowkwto132c0?ixlib=rails-4.2.0&url_params=%7B%3Aw%3D%3E128%2C%20%3Ah%3D%3E128%2C%20%3Afit%3D%3E%22crop%22%2C%20%3Aauto%3D%3E%22format%22%7D"
  },
  {
    "title": "Software Engineer, Klarna",
    "name": "Tobias Kloht",
    "username": "@tkloht",
    "interests": ["Speaking at Events", "Partnering on Side Projects", "Beta testing new products"],
    "img": "https://polywork-production.imgix.net/lanfgpgbqt47zsyylmlcggj92umg?ixlib=rails-4.2.0&url_params=%7B%3Aw%3D%3E128%2C%20%3Ah%3D%3E128%2C%20%3Afit%3D%3E%22crop%22%2C%20%3Aauto%3D%3E%22format%22%7D"
  },
  {
    "title": "General Partner, Bungalow Capital",
    "name": "Dave  Ambrose\n\n\n",
    "username": "@daveambrose",
    "interests": ["Mentoring", "Investing", "Beta testing new products"],
    "img": "https://polywork-production.imgix.net/cwizhe910fsdna3ddrmjhqwjfajk?ixlib=rails-4.2.0&url_params=%7B%3Aw%3D%3E128%2C%20%3Ah%3D%3E128%2C%20%3Afit%3D%3E%22crop%22%2C%20%3Aauto%3D%3E%22format%22%7D"
  },
  {
    "title": "Product Manager - Mobile, Dropbox",
    "name": "Tobias Kemper",
    "username": "@tek",
    "interests": ["Partnering on Side Projects", "Giving resume feedback", "Participating in User Research"],
    "img": "https://polywork-production.imgix.net/71pavfyem6apon403iq4fpme31ub?ixlib=rails-4.2.0&url_params=%7B%3Aw%3D%3E128%2C%20%3Ah%3D%3E128%2C%20%3Afit%3D%3E%22crop%22%2C%20%3Aauto%3D%3E%22format%22%7D"
  },
  {
    "title": "Senior Director of Marketing & Curation, Audiomack",
    "name": "Joe Vango\n\n\n",
    "username": "@joevango",
    "interests": ["Participating in User Research", "Activism", "Joining company boards"],
    "img": "https://polywork-production.imgix.net/cqhhmzpq3957usslbv3qfm5an2y3?ixlib=rails-4.2.0&url_params=%7B%3Aw%3D%3E128%2C%20%3Ah%3D%3E128%2C%20%3Afit%3D%3E%22crop%22%2C%20%3Aauto%3D%3E%22format%22%7D"
  },
  {
    "title": "product manager, GitHub",
    "name": "Bailey Brooks",
    "username": "@baileybrooks",
    "interests": ["Volunteering", "Participating in User Research", "Activism"],
    "img": "https://polywork-production.imgix.net/7sb0278mp71grt54p9zs9w2ujwrb?ixlib=rails-4.2.0&url_params=%7B%3Aw%3D%3E128%2C%20%3Ah%3D%3E128%2C%20%3Afit%3D%3E%22crop%22%2C%20%3Aauto%3D%3E%22format%22%7D"
  },
  {
    "title": "Stafff Developer Evangelist, GitLab",
    "name": "Brendan O'Leary",
    "username": "@brendan",
    "interests": ["Speaking on Clubhouse", "Mentoring", "Guest lecturing"],
    "img": "https://polywork-production.imgix.net/uo2ylsdg9pf6s7n10ej7u1atcmiq?ixlib=rails-4.2.0&url_params=%7B%3Aw%3D%3E128%2C%20%3Ah%3D%3E128%2C%20%3Afit%3D%3E%22crop%22%2C%20%3Aauto%3D%3E%22format%22%7D"
  },
  {
    "title": "Tech Lead Manager, Airtable",
    "name": "Raghav Sethi",
    "username": "@raghavsethi",
    "interests": ["Open Source Contributions", "Guest lecturing", "Volunteering"],
    "img": "https://polywork-production.imgix.net/y3k44tzw90w0nffb31jxdaxxxtfv?ixlib=rails-4.2.0&url_params=%7B%3Aw%3D%3E128%2C%20%3Ah%3D%3E128%2C%20%3Afit%3D%3E%22crop%22%2C%20%3Aauto%3D%3E%22format%22%7D"
  },
  {
    "title": "Head of the Facebook app, Facebook",
    "name": "Fidji Simo",
    "username": "@fidji",
    "interests": ["Guest lecturing", "Speaking on Clubhouse", "Mentoring"],
    "img": "https://polywork-production.imgix.net/19i5zfagi48bi9onjfz97pnmvfli?ixlib=rails-4.2.0&url_params=%7B%3Aw%3D%3E128%2C%20%3Ah%3D%3E128%2C%20%3Afit%3D%3E%22crop%22%2C%20%3Aauto%3D%3E%22format%22%7D"
  },
  {
    "title": "Software Engineer, Airbnb",
    "name": "Andrew Florial",
    "username": "@andrewf",
    "interests": ["Investing", "Raising funding", "Participating in User Research"],
    "img": "https://polywork-production.imgix.net/5wowiakd82bg6zdiv1fqyfwn5nra?ixlib=rails-4.2.0&url_params=%7B%3Aw%3D%3E128%2C%20%3Ah%3D%3E128%2C%20%3Afit%3D%3E%22crop%22%2C%20%3Aauto%3D%3E%22format%22%7D"
  },
  {
    "title": "Creative Technologist, Adobe Inc.",
    "name": "CJ Gammon",
    "username": "@cjgammon",
    "interests": ["Writing", "Content Creation", "Brainstorming"],
    "img": "https://polywork-production.imgix.net/y7dlli3o66gxi3qd9n7mm1hjvisu?ixlib=rails-4.2.0&url_params=%7B%3Aw%3D%3E128%2C%20%3Ah%3D%3E128%2C%20%3Afit%3D%3E%22crop%22%2C%20%3Aauto%3D%3E%22format%22%7D"
  },
  {
    "title": "Software Engineer, Slack",
    "name": "Kishan Patel",
    "username": "@kishan_patel",
    "interests": ["Making Introductions", "Brainstorming"],
    "img": "https://polywork-production.imgix.net/bmw3mkhhfw42ti2vo05rw11e18pa?ixlib=rails-4.2.0&url_params=%7B%3Aw%3D%3E128%2C%20%3Ah%3D%3E128%2C%20%3Afit%3D%3E%22crop%22%2C%20%3Aauto%3D%3E%22format%22%7D"
  },
  {
    "title": "Product Manager, Lyft",
    "name": "Amy Ta",
    "username": "@amyta",
    "interests": ["Partnering on Side Projects", "Joining company boards", "Activism"],
    "img": "https://polywork-production.imgix.net/qzg591bv9iou1c379n98yn46ifrl?ixlib=rails-4.2.0&url_params=%7B%3Aw%3D%3E128%2C%20%3Ah%3D%3E128%2C%20%3Afit%3D%3E%22crop%22%2C%20%3Aauto%3D%3E%22format%22%7D"
  },
  {
    "title": "Developer Advocate, Cloudflare",
    "name": "Jonathan Kuperman",
    "username": "@jkup",
    "interests": ["Open Source Contributions", "Live Streaming", "Investing"],
    "img": "https://polywork-production.imgix.net/6gt349x7cy9hfb11igsjzvo4se8l?ixlib=rails-4.2.0&url_params=%7B%3Aw%3D%3E128%2C%20%3Ah%3D%3E128%2C%20%3Afit%3D%3E%22crop%22%2C%20%3Aauto%3D%3E%22format%22%7D"
  },
  {
    "title": "Founder and General Partner, Kindred Capital",
    "name": "Leila Zegna\n\n\n",
    "username": "@leila",
    "interests": ["Mentoring", "Writing", "Speaking at Events"],
    "img": "https://polywork-production.imgix.net/ysi9pf8hu9ytfah5mqaqvx7vt5uy?ixlib=rails-4.2.0&url_params=%7B%3Aw%3D%3E128%2C%20%3Ah%3D%3E128%2C%20%3Afit%3D%3E%22crop%22%2C%20%3Aauto%3D%3E%22format%22%7D"
  },
  {
    "title": "Director of Product, Design System , The New York Times",
    "name": "Rachel Dixon",
    "username": "@msdixon",
    "interests": ["Participating in User Research", "Guest lecturing", "Open Source Contributions"],
    "img": "https://polywork-production.imgix.net/0cr8pjamp638as0iliabcx9kkgz6?ixlib=rails-4.2.0&url_params=%7B%3Aw%3D%3E128%2C%20%3Ah%3D%3E128%2C%20%3Afit%3D%3E%22crop%22%2C%20%3Aauto%3D%3E%22format%22%7D"
  },
  {
    "title": "Director, Principle Architect, Adobe Inc.",
    "name": "Doug Ross",
    "username": "@sachioross",
    "interests": ["Partnering on Side Projects", "Investing", "Mentoring"],
    "img": "https://polywork-production.imgix.net/81s6t8ml6em38thzdza1j2f6utyf?ixlib=rails-4.2.0&url_params=%7B%3Aw%3D%3E128%2C%20%3Ah%3D%3E128%2C%20%3Afit%3D%3E%22crop%22%2C%20%3Aauto%3D%3E%22format%22%7D"
  },
  {
    "title": "Software Engineer, Apple Inc",
    "name": "Etienne Segonzac",
    "username": "@sgz",
    "interests": ["Giving resume feedback", "Mentoring", "Open Source Contributions"],
    "img": "https://polywork-production.imgix.net/nylpvle32np6713kl9h5sy09n7sw?ixlib=rails-4.2.0&url_params=%7B%3Aw%3D%3E128%2C%20%3Ah%3D%3E128%2C%20%3Afit%3D%3E%22crop%22%2C%20%3Aauto%3D%3E%22format%22%7D"
  },
  {
    "title": "Lead Product Designer, Netflix",
    "name": "Fonz Morris\n\n\n",
    "username": "@fonz",
    "interests": ["Speaking on Clubhouse", "Mentoring", "Guest lecturing"],
    "img": "https://polywork-production.imgix.net/dty99joisz2i11hc1qyoodyfm8se?ixlib=rails-4.2.0&url_params=%7B%3Aw%3D%3E128%2C%20%3Ah%3D%3E128%2C%20%3Afit%3D%3E%22crop%22%2C%20%3Aauto%3D%3E%22format%22%7D"
  },
  {
    "title": "Senior Software Engineer, Netflix",
    "name": "Shaundai Person",
    "username": "@shaundai",
    "interests": ["Open Source Contributions", "Live Streaming", "Content Creation"],
    "img": "https://polywork-production.imgix.net/p6n0yk02f23gl8nzepuxdvnuilg4?ixlib=rails-4.2.0&url_params=%7B%3Aw%3D%3E128%2C%20%3Ah%3D%3E128%2C%20%3Afit%3D%3E%22crop%22%2C%20%3Aauto%3D%3E%22format%22%7D"
  },
  {
    "title": "Software Engineer, Klarna",
    "name": "Jing-Jing Hu",
    "username": "@jingjing142",
    "interests": ["Live Streaming", "Open Source Contributions", "Giving resume feedback"],
    "img": "https://polywork-production.imgix.net/lwgc56nlv75s82wistec8py5x2nk?ixlib=rails-4.2.0&url_params=%7B%3Aw%3D%3E128%2C%20%3Ah%3D%3E128%2C%20%3Afit%3D%3E%22crop%22%2C%20%3Aauto%3D%3E%22format%22%7D"
  },
  {
    "title": "Director of Developer Advocacy, GitHub",
    "name": "Brian Douglas\n\n\n",
    "username": "@bdougie",
    "interests": ["Open Source Contributions", "Guest lecturing", "Live Streaming"],
    "img": "https://polywork-production.imgix.net/aowqh71xhxwtzl3gzknupla57zi6?ixlib=rails-4.2.0&url_params=%7B%3Aw%3D%3E128%2C%20%3Ah%3D%3E128%2C%20%3Afit%3D%3E%22crop%22%2C%20%3Aauto%3D%3E%22format%22%7D"
  },
  {
    "title": "Developer Experience Engineer, Netlify",
    "name": "Ekene Eze",
    "username": "@kenny_io",
    "interests": ["Live Streaming", "Speaking on Clubhouse", "Speaking at Events"],
    "img": "https://polywork-production.imgix.net/gs5z3j8dtp8qsnnhio6hamad8ll5?ixlib=rails-4.2.0&url_params=%7B%3Aw%3D%3E128%2C%20%3Ah%3D%3E128%2C%20%3Afit%3D%3E%22crop%22%2C%20%3Aauto%3D%3E%22format%22%7D"
  },
  {
    "title": "Software Engineer, Coinbase",
    "name": "Savitha Sameerdas",
    "username": "@savitha",
    "interests": ["Investing", "Giving resume feedback", "Guest lecturing"],
    "img": "https://polywork-production.imgix.net/ihjaqqmsn6cs7ju982sofjy4vzok?ixlib=rails-4.2.0&url_params=%7B%3Aw%3D%3E128%2C%20%3Ah%3D%3E128%2C%20%3Afit%3D%3E%22crop%22%2C%20%3Aauto%3D%3E%22format%22%7D"
  },
  {
    "title": "Senior Engineering Manager, GitHub",
    "name": "Denise Yu",
    "username": "@deniseyu",
    "interests": ["Open Source Contributions", "Giving resume feedback", "Guest lecturing"],
    "img": "https://polywork-production.imgix.net/wz14wrnmwh2ri98b6ow7lj76m6dd?ixlib=rails-4.2.0&url_params=%7B%3Aw%3D%3E128%2C%20%3Ah%3D%3E128%2C%20%3Afit%3D%3E%22crop%22%2C%20%3Aauto%3D%3E%22format%22%7D"
  },
  {
    "title": "Head of Strategy & Operations, Dropbox",
    "name": "Kate Kruizenga",
    "username": "@katekruizenga",
    "interests": ["Partnering on Side Projects", "Volunteering", "Mentoring"],
    "img": "https://polywork-production.imgix.net/63pkev600zevmlb7krithvicjnck?ixlib=rails-4.2.0&url_params=%7B%3Aw%3D%3E128%2C%20%3Ah%3D%3E128%2C%20%3Afit%3D%3E%22crop%22%2C%20%3Aauto%3D%3E%22format%22%7D"
  },
  {
    "title": "Accessibility Software Engineer, GitHub",
    "name": "Amélia Chavot",
    "username": "@artemisia",
    "interests": ["Beta testing new products", "Joining company boards", "Mentoring"],
    "img": "https://polywork-production.imgix.net/vgnesq2ruhj3lq4abxwr4td8sne5?ixlib=rails-4.2.0&url_params=%7B%3Aw%3D%3E128%2C%20%3Ah%3D%3E128%2C%20%3Afit%3D%3E%22crop%22%2C%20%3Aauto%3D%3E%22format%22%7D"
  },
  {
    "title": "Engineering Manager, Slack",
    "name": "Kimberly Munoz",
    "username": "@kimberlymunoz",
    "interests": ["Beta testing new products"],
    "img": "https://polywork-production.imgix.net/nysvybko6nftfx7ayd5xmjdk4jpp?ixlib=rails-4.2.0&url_params=%7B%3Aw%3D%3E128%2C%20%3Ah%3D%3E128%2C%20%3Afit%3D%3E%22crop%22%2C%20%3Aauto%3D%3E%22format%22%7D"
  },
  {
    "title": "Product Director, Sidewalk Labs",
    "name": "Veronica Pinchin\n\n\n",
    "username": "@vp",
    "interests": ["Advising companies", "Mentoring", "Speaking at Events"],
    "img": "https://polywork-production.imgix.net/uai12j2ve7pwugxsnjvp109f5ovv?ixlib=rails-4.2.0&url_params=%7B%3Aw%3D%3E128%2C%20%3Ah%3D%3E128%2C%20%3Afit%3D%3E%22crop%22%2C%20%3Aauto%3D%3E%22format%22%7D"
  },
  {
    "title": "Product Designer, Design Systems, Twitter",
    "name": "Joey Banks\n\n\n",
    "username": "@joeyabanks",
    "interests": ["Open Source Contributions", "Giving resume feedback", "Live Streaming"],
    "img": "https://polywork-production.imgix.net/z4q75fhgw7fue7mlozxtbg01v7bu?ixlib=rails-4.2.0&url_params=%7B%3Aw%3D%3E128%2C%20%3Ah%3D%3E128%2C%20%3Afit%3D%3E%22crop%22%2C%20%3Aauto%3D%3E%22format%22%7D"
  },
  {
    "title": "Product lead, Stripe",
    "name": "Kenneth Auchenberg",
    "username": "@auchenberg",
    "interests": ["Partnering on Side Projects"],
    "img": "https://polywork-production.imgix.net/rg7b16bpxb3knrugfj06gos0e650?ixlib=rails-4.2.0&url_params=%7B%3Aw%3D%3E128%2C%20%3Ah%3D%3E128%2C%20%3Afit%3D%3E%22crop%22%2C%20%3Aauto%3D%3E%22format%22%7D"
  },
  {
    "title": "",
    "name": "Matthew Ziskie\n\n\n",
    "username": "@matt",
    "interests": ["Speaking at Events", "Guest lecturing", "Investing"],
    "img": "https://polywork-production.imgix.net/aeanb0eulu6u8ojn87kdb31taxyw?ixlib=rails-4.2.0&url_params=%7B%3Aw%3D%3E128%2C%20%3Ah%3D%3E128%2C%20%3Afit%3D%3E%22crop%22%2C%20%3Aauto%3D%3E%22format%22%7D"
  },
  {
    "title": "Software Engineer, Stripe",
    "name": "Bolaji Fatade",
    "username": "@boj",
    "interests": ["Investing", "Volunteering", "Participating in User Research"],
    "img": "https://polywork-production.imgix.net/acow4w9pk4tjh99wt4dpruyk17ys?ixlib=rails-4.2.0&url_params=%7B%3Aw%3D%3E128%2C%20%3Ah%3D%3E128%2C%20%3Afit%3D%3E%22crop%22%2C%20%3Aauto%3D%3E%22format%22%7D"
  },
  {
    "title": "Design Technologist, Spotify",
    "name": "Gautham Sajith",
    "username": "@gautham",
    "interests": ["Speaking at Events", "Guest lecturing", "Beta testing new products"],
    "img": "https://polywork-production.imgix.net/p0f4yap9zm13lefo9uk085azehkv?ixlib=rails-4.2.0&url_params=%7B%3Aw%3D%3E128%2C%20%3Ah%3D%3E128%2C%20%3Afit%3D%3E%22crop%22%2C%20%3Aauto%3D%3E%22format%22%7D"
  },
  {
    "title": "Senior Software Engineer, Calendly",
    "name": "Doug Tykocki",
    "username": "@dtykocki",
    "interests": ["Open Source Contributions", "Mentoring"],
    "img": "https://polywork-production.imgix.net/nukuyb9wglidwprqngr8halhv9vu?ixlib=rails-4.2.0&url_params=%7B%3Aw%3D%3E128%2C%20%3Ah%3D%3E128%2C%20%3Afit%3D%3E%22crop%22%2C%20%3Aauto%3D%3E%22format%22%7D"
  },
  {
    "title": "Senior Developer Advocate, Amazon Web Services",
    "name": "Ali Spittel\n\n\n",
    "username": "@ali",
    "interests": ["Content Creation", "Speaking at Events", "Writing"],
    "img": "https://polywork-production.imgix.net/oly4fnxc0qbxmcf1hbm9dheyjxtm?ixlib=rails-4.2.0&url_params=%7B%3Aw%3D%3E128%2C%20%3Ah%3D%3E128%2C%20%3Afit%3D%3E%22crop%22%2C%20%3Aauto%3D%3E%22format%22%7D"
  },
  {
    "title": "Sr. Engineering Manager, HubSpot",
    "name": "Richa Khandelwal",
    "username": "@richa",
    "interests": ["Giving resume feedback", "Joining company boards", "Speaking at Events"],
    "img": "https://polywork-production.imgix.net/h3tq87604qi6rrzqjszyet6l0psl?ixlib=rails-4.2.0&url_params=%7B%3Aw%3D%3E128%2C%20%3Ah%3D%3E128%2C%20%3Afit%3D%3E%22crop%22%2C%20%3Aauto%3D%3E%22format%22%7D"
  },
  {
    "title": "Tech Lead - Revenue & Subscriptions Analytics, Discord",
    "name": "Sam Garfield",
    "username": "@garfieldsam",
    "interests": ["Partnering on Side Projects", "Open Source Contributions", "Giving resume feedback"],
    "img": "https://polywork-production.imgix.net/jimyymuclok0ns340y9j7639v66e?ixlib=rails-4.2.0&url_params=%7B%3Aw%3D%3E128%2C%20%3Ah%3D%3E128%2C%20%3Afit%3D%3E%22crop%22%2C%20%3Aauto%3D%3E%22format%22%7D"
  },
  {
    "title": "Developer Advocate, Twitch",
    "name": "Diana Rodriguez",
    "username": "@cotufa82",
    "interests": ["Open Source Contributions", "Guest lecturing", "Raising funding"],
    "img": "https://polywork-production.imgix.net/g6kr0qd909ce4nx8vei3n5tkmfap?ixlib=rails-4.2.0&url_params=%7B%3Aw%3D%3E128%2C%20%3Ah%3D%3E128%2C%20%3Afit%3D%3E%22crop%22%2C%20%3Aauto%3D%3E%22format%22%7D"
  },
  {
    "title": "Software Engineer, Stripe",
    "name": "Conner Bean",
    "username": "@csb",
    "interests": ["Open Source Contributions", "Investing", "Giving resume feedback"],
    "img": "https://polywork-production.imgix.net/xt3qubz1j6eyek79ba0xuxd92cx0?ixlib=rails-4.2.0&url_params=%7B%3Aw%3D%3E128%2C%20%3Ah%3D%3E128%2C%20%3Afit%3D%3E%22crop%22%2C%20%3Aauto%3D%3E%22format%22%7D"
  },
  {
    "title": "Interaction Designer, Google",
    "name": "Nancy Lee",
    "username": "@nancylee",
    "interests": ["Activism", "Mentoring", "Writing"],
    "img": "https://polywork-production.imgix.net/qauzz1f9sju0vlec04xi8ss84ax5?ixlib=rails-4.2.0&url_params=%7B%3Aw%3D%3E128%2C%20%3Ah%3D%3E128%2C%20%3Afit%3D%3E%22crop%22%2C%20%3Aauto%3D%3E%22format%22%7D"
  },
  {
    "title": "Slack Fund, Slack",
    "name": "Dillon Ferdinandi",
    "username": "@dillonfrd",
    "interests": ["Giving resume feedback", "Guest lecturing", "Volunteering"],
    "img": "https://polywork-production.imgix.net/gwmmxpg57la69hps25vit30bnf0r?ixlib=rails-4.2.0&url_params=%7B%3Aw%3D%3E128%2C%20%3Ah%3D%3E128%2C%20%3Afit%3D%3E%22crop%22%2C%20%3Aauto%3D%3E%22format%22%7D"
  },
  {
    "title": "Director of Engineering, Slack",
    "name": "Sean Herron",
    "username": "@seanherron",
    "interests": ["Giving resume feedback", "Activism", "Joining company boards"],
    "img": "https://polywork-production.imgix.net/6z6el7acuco2dgu3whutglpc3exf?ixlib=rails-4.2.0&url_params=%7B%3Aw%3D%3E128%2C%20%3Ah%3D%3E128%2C%20%3Afit%3D%3E%22crop%22%2C%20%3Aauto%3D%3E%22format%22%7D"
  },
  {
    "title": "Senior Front-end Engineer, Coinbase",
    "name": "Dan Cortes",
    "username": "@dan_cortes_",
    "interests": ["Live Streaming", "Open Source Contributions", "Speaking at Events"],
    "img": "https://polywork-production.imgix.net/jqav4czjonuj7bpnzhni2jj1c1zx?ixlib=rails-4.2.0&url_params=%7B%3Aw%3D%3E128%2C%20%3Ah%3D%3E128%2C%20%3Afit%3D%3E%22crop%22%2C%20%3Aauto%3D%3E%22format%22%7D"
  },
  {
    "title": "Staff Engineering Manager, Design Infrastructure, GitHub",
    "name": "Leslie Cohn-Wein",
    "username": "@lesliecdubs",
    "interests": ["Participating in User Research", "Live Streaming", "Speaking at Events"],
    "img": "https://polywork-production.imgix.net/5gw4h0f1lm6v6s0280v5j3fabp0i?ixlib=rails-4.2.0&url_params=%7B%3Aw%3D%3E128%2C%20%3Ah%3D%3E128%2C%20%3Afit%3D%3E%22crop%22%2C%20%3Aauto%3D%3E%22format%22%7D"
  },
  {
    "title": "Software Engineer, Airtable",
    "name": "Vu Tran",
    "username": "@vutran",
    "interests": ["Open Source Contributions", "Live Streaming", "Mentoring"],
    "img": "https://polywork-production.imgix.net/8cnx1tca3dkqpsq487lw10ulm8pg?ixlib=rails-4.2.0&url_params=%7B%3Aw%3D%3E128%2C%20%3Ah%3D%3E128%2C%20%3Afit%3D%3E%22crop%22%2C%20%3Aauto%3D%3E%22format%22%7D"
  },
  {
    "title": "Senior Brand Designer, Airtable",
    "name": "Kim  Pham",
    "username": "@kimpham",
    "interests": ["Philanthropy", "Full time roles", "Giving resume feedback"],
    "img": "https://polywork-production.imgix.net/lqqo220ufsgeh554fhvldxpifd8n?ixlib=rails-4.2.0&url_params=%7B%3Aw%3D%3E128%2C%20%3Ah%3D%3E128%2C%20%3Afit%3D%3E%22crop%22%2C%20%3Aauto%3D%3E%22format%22%7D"
  },
  {
    "title": "Principal, Index Ventures",
    "name": "Dino Becirovic",
    "username": "@dino",
    "interests": ["Advising companies", "Writing", "Investing"],
    "img": "https://polywork-production.imgix.net/tvtsdn7sg8x1sk9tzgmpcw16ytnj?ixlib=rails-4.2.0&url_params=%7B%3Aw%3D%3E128%2C%20%3Ah%3D%3E128%2C%20%3Afit%3D%3E%22crop%22%2C%20%3Aauto%3D%3E%22format%22%7D"
  },
  {
    "title": "Senior Product Manager, Coinbase",
    "name": "Rishav Mukherji",
    "username": "@rishm",
    "interests": ["Investing", "Beta testing new products"],
    "img": "https://polywork-production.imgix.net/swo0sy6a79dsqrfvsa3v1tu3lrc3?ixlib=rails-4.2.0&url_params=%7B%3Aw%3D%3E128%2C%20%3Ah%3D%3E128%2C%20%3Afit%3D%3E%22crop%22%2C%20%3Aauto%3D%3E%22format%22%7D"
  },
  {
    "title": "Project Manager, Hashnode",
    "name": "Sumudu Siriwardana",
    "username": "@sumusiriwardana",
    "interests": ["Mentoring", "Writing", "Brainstorming"],
    "img": "https://polywork-production.imgix.net/v772ln2uyoo65gbjbl57ljmha0jm?ixlib=rails-4.2.0&url_params=%7B%3Aw%3D%3E128%2C%20%3Ah%3D%3E128%2C%20%3Afit%3D%3E%22crop%22%2C%20%3Aauto%3D%3E%22format%22%7D"
  },
  {
    "title": "Senior Software Engineer, Klarna",
    "name": "Tahir Ahmed",
    "username": "@tahirahmed",
    "interests": ["Investing", "Mentoring", "Brainstorming"],
    "img": "https://polywork-production.imgix.net/atfj4jd0f1ax6athr5fl4re7idp2?ixlib=rails-4.2.0&url_params=%7B%3Aw%3D%3E128%2C%20%3Ah%3D%3E128%2C%20%3Afit%3D%3E%22crop%22%2C%20%3Aauto%3D%3E%22format%22%7D"
  },
  {
    "title": "Head of Design, Gem",
    "name": "Tanner Christensen",
    "username": "@tannerc",
    "interests": ["Guest lecturing", "Speaking at Events", "Writing"],
    "img": "https://polywork-production.imgix.net/h8v33phrmvi06eqvk8dyesv3qdvd?ixlib=rails-4.2.0&url_params=%7B%3Aw%3D%3E128%2C%20%3Ah%3D%3E128%2C%20%3Afit%3D%3E%22crop%22%2C%20%3Aauto%3D%3E%22format%22%7D"
  },
  {
    "title": "Software Engineer, Instabug",
    "name": "Hassan ElDesouky",
    "username": "@hassaneldesouky",
    "interests": ["Giving resume feedback"],
    "img": "https://polywork-production.imgix.net/1e530rtvani04ymw8uc2vyrqfiv9?ixlib=rails-4.2.0&url_params=%7B%3Aw%3D%3E128%2C%20%3Ah%3D%3E128%2C%20%3Afit%3D%3E%22crop%22%2C%20%3Aauto%3D%3E%22format%22%7D"
  },
  {
    "title": "Product Manager, Afterpay",
    "name": "Matt Yao",
    "username": "@mattyao",
    "interests": ["Full time roles", "Philanthropy", "Partnering on Side Projects"],
    "img": "https://polywork-production.imgix.net/1z069fx1atwwhcg84jpey1bl6yrw?ixlib=rails-4.2.0&url_params=%7B%3Aw%3D%3E128%2C%20%3Ah%3D%3E128%2C%20%3Afit%3D%3E%22crop%22%2C%20%3Aauto%3D%3E%22format%22%7D"
  },
  {
    "title": "Engineering Manager, Spotify",
    "name": "Emily Kowal",
    "username": "@emottk",
    "interests": ["Guest lecturing", "Open Source Contributions", "Writing"],
    "img": "https://polywork-production.imgix.net/unypdnyf4durqlpibnygpfh6glwq?ixlib=rails-4.2.0&url_params=%7B%3Aw%3D%3E128%2C%20%3Ah%3D%3E128%2C%20%3Afit%3D%3E%22crop%22%2C%20%3Aauto%3D%3E%22format%22%7D"
  },
  {
    "title": "Sr. Community Manager, Zapier",
    "name": "Nick Simard\n\n\n",
    "username": "@nicksimard",
    "interests": ["Beta testing new products", "Writing", "Participating in User Research"],
    "img": "https://polywork-production.imgix.net/pkqrlqxrvut77cxvy0eu4lluuxrw?ixlib=rails-4.2.0&url_params=%7B%3Aw%3D%3E128%2C%20%3Ah%3D%3E128%2C%20%3Afit%3D%3E%22crop%22%2C%20%3Aauto%3D%3E%22format%22%7D"
  },
  {
    "title": "Product Engineer, Airtable",
    "name": "Caleb Meredith",
    "username": "@calebmer",
    "interests": ["Content Creation", "Live Streaming", "Speaking on Clubhouse"],
    "img": "https://polywork-production.imgix.net/rqkaahxkzffwzqdr69t8hbggkl1o?ixlib=rails-4.2.0&url_params=%7B%3Aw%3D%3E128%2C%20%3Ah%3D%3E128%2C%20%3Afit%3D%3E%22crop%22%2C%20%3Aauto%3D%3E%22format%22%7D"
  },
  {
    "title": "Senior Product Marketing Manager, The New York Times",
    "name": "Amit Sankaran",
    "username": "@amitsankaran",
    "interests": ["Giving resume feedback", "Volunteering", "Participating in User Research"],
    "img": "https://polywork-production.imgix.net/8a4ydq48ssmln57uze5bwxjdm4k8?ixlib=rails-4.2.0&url_params=%7B%3Aw%3D%3E128%2C%20%3Ah%3D%3E128%2C%20%3Afit%3D%3E%22crop%22%2C%20%3Aauto%3D%3E%22format%22%7D"
  },
  {
    "title": "Product Marketing Manager, Spotify",
    "name": "Adam Kane",
    "username": "@kaneing",
    "interests": ["Beta testing new products", "Speaking on Clubhouse", "Mentoring"],
    "img": "https://polywork-production.imgix.net/nuk413fsuazvvnhh678iy1tldz8a?ixlib=rails-4.2.0&url_params=%7B%3Aw%3D%3E128%2C%20%3Ah%3D%3E128%2C%20%3Afit%3D%3E%22crop%22%2C%20%3Aauto%3D%3E%22format%22%7D"
  },
  {
    "title": "Software Engineering Manager, Coinbase",
    "name": "Manan Patel",
    "username": "@manan",
    "interests": ["Mentoring", "Investing", "Advising companies"],
    "img": "https://polywork-production.imgix.net/jdakq5jsaale1fnz055v477b4dcf?ixlib=rails-4.2.0&url_params=%7B%3Aw%3D%3E128%2C%20%3Ah%3D%3E128%2C%20%3Afit%3D%3E%22crop%22%2C%20%3Aauto%3D%3E%22format%22%7D"
  },
  {
    "title": "Director, TwitchCon & Community Events, Twitch",
    "name": "Krystal Herring",
    "username": "@siren",
    "interests": ["Partnering on Side Projects", "Volunteering", "Joining company boards"],
    "img": "https://polywork-production.imgix.net/stu9bnp6u9ur7ox1xdqbs8svh1me?ixlib=rails-4.2.0&url_params=%7B%3Aw%3D%3E128%2C%20%3Ah%3D%3E128%2C%20%3Afit%3D%3E%22crop%22%2C%20%3Aauto%3D%3E%22format%22%7D"
  },
  {
    "title": "Senior Software Engineer, Airbnb",
    "name": "Jose Santos\n\n\n",
    "username": "@josesantos",
    "interests": ["Investing"],
    "img": "https://polywork-production.imgix.net/4jlohy2p7gldcyc2hrq57qs1et2e?ixlib=rails-4.2.0&url_params=%7B%3Aw%3D%3E128%2C%20%3Ah%3D%3E128%2C%20%3Afit%3D%3E%22crop%22%2C%20%3Aauto%3D%3E%22format%22%7D"
  },
  {
    "title": "Director, Data, Netlify",
    "name": "Emilie Schario",
    "username": "@emilieschario",
    "interests": ["Beta testing new products", "Joining company boards", "Speaking on Clubhouse"],
    "img": "https://polywork-production.imgix.net/xotcn5uozs79342kqeqh6cl57t32?ixlib=rails-4.2.0&url_params=%7B%3Aw%3D%3E128%2C%20%3Ah%3D%3E128%2C%20%3Afit%3D%3E%22crop%22%2C%20%3Aauto%3D%3E%22format%22%7D"
  },
  {
    "title": "Group Product Manager, Netlify",
    "name": "Joel Cloralt\n\n\n",
    "username": "@joelcloralt",
    "interests": ["Beta testing new products", "Advising companies"],
    "img": "https://polywork-production.imgix.net/kjj9rhka9ejbyk7xic7eenl4kew4?ixlib=rails-4.2.0&url_params=%7B%3Aw%3D%3E128%2C%20%3Ah%3D%3E128%2C%20%3Afit%3D%3E%22crop%22%2C%20%3Aauto%3D%3E%22format%22%7D"
  },
  {
    "title": "Product Operations, Instacart",
    "name": "Zilaida Salgueiro",
    "username": "@zilaida",
    "interests": ["Guest lecturing", "Participating in User Research", "Speaking on Clubhouse"],
    "img": "https://polywork-production.imgix.net/zqzc4q6f7vhlfhrh3d41sjf69p9u?ixlib=rails-4.2.0&url_params=%7B%3Aw%3D%3E128%2C%20%3Ah%3D%3E128%2C%20%3Afit%3D%3E%22crop%22%2C%20%3Aauto%3D%3E%22format%22%7D"
  },
  {
    "title": "Senior Software Engineer, Netflix",
    "name": "Michelle Brenner",
    "username": "@michellelynneb",
    "interests": ["Guest lecturing", "Studio Sessions", "Writing"],
    "img": "https://polywork-production.imgix.net/0z7duvk7slknfy6vxk9raotzuvr2?ixlib=rails-4.2.0&url_params=%7B%3Aw%3D%3E128%2C%20%3Ah%3D%3E128%2C%20%3Afit%3D%3E%22crop%22%2C%20%3Aauto%3D%3E%22format%22%7D"
  },
  {
    "title": "Senior Software Engineer, The Walt Disney Company",
    "name": "Roy Sivan",
    "username": "@royboy789",
    "interests": ["Mentoring", "Beta testing new products", "Speaking at Events"],
    "img": "https://polywork-production.imgix.net/nji12b4bt41zkjcsmex0dwszv2s2?ixlib=rails-4.2.0&url_params=%7B%3Aw%3D%3E128%2C%20%3Ah%3D%3E128%2C%20%3Afit%3D%3E%22crop%22%2C%20%3Aauto%3D%3E%22format%22%7D"
  },
  {
    "title": "Co-Founder, Wonderpath",
    "name": "Tanya Sharma\n\n\n",
    "username": "@tanyasharma",
    "interests": ["Participating in User Research", "Giving resume feedback", "Mentoring"],
    "img": "https://polywork-production.imgix.net/jxptx9mj89p7qhadxf7ln8801jad?ixlib=rails-4.2.0&url_params=%7B%3Aw%3D%3E128%2C%20%3Ah%3D%3E128%2C%20%3Afit%3D%3E%22crop%22%2C%20%3Aauto%3D%3E%22format%22%7D"
  },
  {
    "title": "Senior Software Engineer, Zapier",
    "name": "David Brownman",
    "username": "@xavdid",
    "interests": ["Open Source Contributions", "Beta testing new products", "Writing"],
    "img": "https://polywork-production.imgix.net/ldy4v14zd7v5y47lzk93ywe4gmjx?ixlib=rails-4.2.0&url_params=%7B%3Aw%3D%3E128%2C%20%3Ah%3D%3E128%2C%20%3Afit%3D%3E%22crop%22%2C%20%3Aauto%3D%3E%22format%22%7D"
  },
  {
    "title": "Co-founder, Instacart",
    "name": "Max Mullen\n\n\n",
    "username": "@maxmullen",
    "interests": ["Investing"],
    "img": "https://polywork-production.imgix.net/7aqq8fhdx67pewjy81qfu1rd1cx6?ixlib=rails-4.2.0&url_params=%7B%3Aw%3D%3E128%2C%20%3Ah%3D%3E128%2C%20%3Afit%3D%3E%22crop%22%2C%20%3Aauto%3D%3E%22format%22%7D"
  },
  {
    "title": "Director of Research, Office of the CTO, GitHub",
    "name": "Idan Gazit\n\n\n",
    "username": "@idan",
    "interests": ["Advising companies", "Mentoring", "Guest lecturing"],
    "img": "https://polywork-production.imgix.net/5rvy05gc7rcgv9w8d4l0n4bc4zal?ixlib=rails-4.2.0&url_params=%7B%3Aw%3D%3E128%2C%20%3Ah%3D%3E128%2C%20%3Afit%3D%3E%22crop%22%2C%20%3Aauto%3D%3E%22format%22%7D"
  },
  {
    "title": "Staff product designer, Stripe",
    "name": "Karolis Kosas",
    "username": "@karoliskosas",
    "interests": ["Guest lecturing"],
    "img": "https://polywork-production.imgix.net/mtvs5l4lz617gnxcc5a3a37l0fvk?ixlib=rails-4.2.0&url_params=%7B%3Aw%3D%3E128%2C%20%3Ah%3D%3E128%2C%20%3Afit%3D%3E%22crop%22%2C%20%3Aauto%3D%3E%22format%22%7D"
  },
  {
    "title": "Sr. Product Design Manager , Waze",
    "name": "Yatir Kaaren",
    "username": "@yatir",
    "interests": ["Giving resume feedback", "Guest lecturing", "Mentoring"],
    "img": "https://polywork-production.imgix.net/l319rsbgywo4ab0lcoqxbpgvztlj?ixlib=rails-4.2.0&url_params=%7B%3Aw%3D%3E128%2C%20%3Ah%3D%3E128%2C%20%3Afit%3D%3E%22crop%22%2C%20%3Aauto%3D%3E%22format%22%7D"
  },
  {
    "title": "Co-Founder & President, Lyft",
    "name": "John Zimmer\n\n\n",
    "username": "@john",
    "interests": ["Philanthropy", "Investing", "Volunteering"],
    "img": "https://polywork-production.imgix.net/ru0t693x5fe217wk9q0vanr1nffm?ixlib=rails-4.2.0&url_params=%7B%3Aw%3D%3E128%2C%20%3Ah%3D%3E128%2C%20%3Afit%3D%3E%22crop%22%2C%20%3Aauto%3D%3E%22format%22%7D"
  },
  {
    "title": "VP Product, LinkedIn",
    "name": "Blake Barnes",
    "username": "@blakebarnes",
    "interests": ["Investing", "Joining company boards", "Advising companies"],
    "img": "https://polywork-production.imgix.net/ytxwut7k8qduj61egsw6x48fxnuo?ixlib=rails-4.2.0&url_params=%7B%3Aw%3D%3E128%2C%20%3Ah%3D%3E128%2C%20%3Afit%3D%3E%22crop%22%2C%20%3Aauto%3D%3E%22format%22%7D"
  },
  {
    "title": "Designer, Rainbow",
    "name": "Jeremy Goldberg\n\n\n",
    "username": "@jeremygoldberg",
    "interests": ["Investing", "Advising companies"],
    "img": "https://polywork-production.imgix.net/inlz0obif69kp7szub46qovhj9g9?ixlib=rails-4.2.0&url_params=%7B%3Aw%3D%3E128%2C%20%3Ah%3D%3E128%2C%20%3Afit%3D%3E%22crop%22%2C%20%3Aauto%3D%3E%22format%22%7D"
  },
  {
    "title": "Senior Software Engineer - Android, Slack",
    "name": "Tinashe Mzondiwa",
    "username": "@tinashe",
    "interests": ["Beta testing new products", "Mentoring", "Open Source Contributions"],
    "img": "https://polywork-production.imgix.net/w16kplkrrs7n3yk3s1eyb9mwlu3q?ixlib=rails-4.2.0&url_params=%7B%3Aw%3D%3E128%2C%20%3Ah%3D%3E128%2C%20%3Afit%3D%3E%22crop%22%2C%20%3Aauto%3D%3E%22format%22%7D"
  },
  {
    "title": "Software Engineering Manager, Apple Inc",
    "name": "Sierra Murphy",
    "username": "@sierramp",
    "interests": ["Volunteering", "Brainstorming"],
    "img": "https://polywork-production.imgix.net/p7f6ip8r56y9klya7c3kzi22joka?ixlib=rails-4.2.0&url_params=%7B%3Aw%3D%3E128%2C%20%3Ah%3D%3E128%2C%20%3Afit%3D%3E%22crop%22%2C%20%3Aauto%3D%3E%22format%22%7D"
  },
  {
    "title": "Engineering Director, Instagram",
    "name": "Yoav Shapira",
    "username": "@yoavshapira",
    "interests": ["Guest lecturing", "Speaking at Events", "Philanthropy"],
    "img": "https://polywork-production.imgix.net/z6u0r8anj9mlde3luc2d25hspwxn?ixlib=rails-4.2.0&url_params=%7B%3Aw%3D%3E128%2C%20%3Ah%3D%3E128%2C%20%3Afit%3D%3E%22crop%22%2C%20%3Aauto%3D%3E%22format%22%7D"
  },
  {
    "title": "Senior Product Manager , Fiverr",
    "name": "Roi Cohen",
    "username": "@roicohen",
    "interests": ["Guest lecturing", "Writing", "Advising companies"],
    "img": "https://polywork-production.imgix.net/s7280mkkq5mr0qyo760syq82ojxj?ixlib=rails-4.2.0&url_params=%7B%3Aw%3D%3E128%2C%20%3Ah%3D%3E128%2C%20%3Afit%3D%3E%22crop%22%2C%20%3Aauto%3D%3E%22format%22%7D"
  },
  {
    "title": "Senior Product Designer, Brex",
    "name": "Ramy Majouji",
    "username": "@majouji",
    "interests": ["Giving resume feedback", "Investing"],
    "img": "https://polywork-production.imgix.net/o7zwmejqxxrxqbdg7su30f1xd411?ixlib=rails-4.2.0&url_params=%7B%3Aw%3D%3E128%2C%20%3Ah%3D%3E128%2C%20%3Afit%3D%3E%22crop%22%2C%20%3Aauto%3D%3E%22format%22%7D"
  },
  {
    "title": "Product, Stripe",
    "name": "Jeff Weinstein",
    "username": "@jweinstein",
    "interests": ["Investing"],
    "img": "https://polywork-production.imgix.net/s7zbtag3znbwzc2tc0lv05pjzajp?ixlib=rails-4.2.0&url_params=%7B%3Aw%3D%3E128%2C%20%3Ah%3D%3E128%2C%20%3Afit%3D%3E%22crop%22%2C%20%3Aauto%3D%3E%22format%22%7D"
  },
  {
    "title": "Senior developer advocate, Stripe",
    "name": "Charlie Gerard",
    "username": "@devdevcharlie",
    "interests": ["Beta testing new products", "Mentoring", "Speaking on Clubhouse"],
    "img": "https://polywork-production.imgix.net/vnqexlicvg58195lvgi2dv38d16l?ixlib=rails-4.2.0&url_params=%7B%3Aw%3D%3E128%2C%20%3Ah%3D%3E128%2C%20%3Afit%3D%3E%22crop%22%2C%20%3Aauto%3D%3E%22format%22%7D"
  },
  {
    "title": "Senior Staff Product Designer, Slack",
    "name": "Kyle Turman",
    "username": "@turman",
    "interests": ["Partnering on Side Projects", "Philanthropy", "Investing"],
    "img": "https://polywork-production.imgix.net/fxblbtb0afcd2tixxqjycmb1ni2k?ixlib=rails-4.2.0&url_params=%7B%3Aw%3D%3E128%2C%20%3Ah%3D%3E128%2C%20%3Afit%3D%3E%22crop%22%2C%20%3Aauto%3D%3E%22format%22%7D"
  },
  {
    "title": "Art Director, Zapier",
    "name": "Jon Schafer",
    "username": "@jonaschafer",
    "interests": ["Joining company boards", "Mentoring", "Writing"],
    "img": "https://polywork-production.imgix.net/90fp9p32visaubrcectmjea1n1o4?ixlib=rails-4.2.0&url_params=%7B%3Aw%3D%3E128%2C%20%3Ah%3D%3E128%2C%20%3Afit%3D%3E%22crop%22%2C%20%3Aauto%3D%3E%22format%22%7D"
  },
  {
    "title": "Product Manager, Amazon",
    "name": "Jen Aprahamian",
    "username": "@jennifermarie",
    "interests": ["Content Creation", "Beta testing new products", "Participating in User Research"],
    "img": "https://polywork-production.imgix.net/hh25lfsvun1j8e0ybbfuvf353c3h?ixlib=rails-4.2.0&url_params=%7B%3Aw%3D%3E128%2C%20%3Ah%3D%3E128%2C%20%3Afit%3D%3E%22crop%22%2C%20%3Aauto%3D%3E%22format%22%7D"
  },
  {
    "title": "Head of Developer Advocacy, Slack",
    "name": "Colm Doyle\n\n\n",
    "username": "@colmdoyle",
    "interests": ["Speaking at Events", "Writing", "Advising companies"],
    "img": "https://polywork-production.imgix.net/nqu0xyp4tx0955ohrc7v721b1ylw?ixlib=rails-4.2.0&url_params=%7B%3Aw%3D%3E128%2C%20%3Ah%3D%3E128%2C%20%3Afit%3D%3E%22crop%22%2C%20%3Aauto%3D%3E%22format%22%7D"
  },
  {
    "title": "Software Engineering Manager, Netflix",
    "name": "Nazanin Delam",
    "username": "@nazdelam",
    "interests": ["Investing", "Giving resume feedback"],
    "img": "https://polywork-production.imgix.net/0fz65yq6jm6lqs6ieluu7d2bbexn?ixlib=rails-4.2.0&url_params=%7B%3Aw%3D%3E128%2C%20%3Ah%3D%3E128%2C%20%3Afit%3D%3E%22crop%22%2C%20%3Aauto%3D%3E%22format%22%7D"
  },
  {
    "title": "Co-Founder, SVP, Operations, Audiomack",
    "name": "Brian Zisook\n\n\n",
    "username": "@bz",
    "interests": ["Joining company boards", "Guest lecturing", "Speaking at Events"],
    "img": "https://polywork-production.imgix.net/t2757q1ze80dpxgrvhm9gglcmhdh?ixlib=rails-4.2.0&url_params=%7B%3Aw%3D%3E128%2C%20%3Ah%3D%3E128%2C%20%3Afit%3D%3E%22crop%22%2C%20%3Aauto%3D%3E%22format%22%7D"
  },
  {
    "title": "supply lead, AirGarage",
    "name": "Bryan Sbriglia",
    "username": "@bryansbriglia",
    "interests": ["Writing", "Giving resume feedback", "Mentoring"],
    "img": "https://polywork-production.imgix.net/581e5d9uyvz2oddsfn5dfdi974vi?ixlib=rails-4.2.0&url_params=%7B%3Aw%3D%3E128%2C%20%3Ah%3D%3E128%2C%20%3Afit%3D%3E%22crop%22%2C%20%3Aauto%3D%3E%22format%22%7D"
  },
  {
    "title": "Senior Developer Advocate, AWS",
    "name": "Jacquie Grindrod",
    "username": "@gogococo",
    "interests": ["Open Source Contributions", "Guest lecturing", "Live Streaming"],
    "img": "https://polywork-production.imgix.net/qi5rnzqeuxhxavg374n2rlg1xmu6?ixlib=rails-4.2.0&url_params=%7B%3Aw%3D%3E128%2C%20%3Ah%3D%3E128%2C%20%3Afit%3D%3E%22crop%22%2C%20%3Aauto%3D%3E%22format%22%7D"
  },
  {
    "title": "Head of Podcaster / Co-Founder Anchor, Spotify",
    "name": "Michael Mignano\n\n\n",
    "username": "@mignano",
    "interests": ["Guest lecturing", "Investing", "Speaking at Events"],
    "img": "https://polywork-production.imgix.net/7werupd6r9k9u2krxxe308yxj7e6?ixlib=rails-4.2.0&url_params=%7B%3Aw%3D%3E128%2C%20%3Ah%3D%3E128%2C%20%3Afit%3D%3E%22crop%22%2C%20%3Aauto%3D%3E%22format%22%7D"
  },
  {
    "title": "",
    "name": "Mark McLaughlin\n\n\n",
    "username": "@clocky",
    "interests": ["Giving resume feedback", "Beta testing new products", "Participating in User Research"],
    "img": "https://polywork-production.imgix.net/301lhg7filiw5deabric9d2s867q?ixlib=rails-4.2.0&url_params=%7B%3Aw%3D%3E128%2C%20%3Ah%3D%3E128%2C%20%3Afit%3D%3E%22crop%22%2C%20%3Aauto%3D%3E%22format%22%7D"
  },
  {
    "title": "Software Engineer, Coinbase",
    "name": "Ellie Huxtable",
    "username": "@ellieh",
    "interests": ["Mentoring", "Beta testing new products", "Speaking at Events"],
    "img": "https://polywork-production.imgix.net/wf36xn1fzyz0yj4hkeb88v0npdlk?ixlib=rails-4.2.0&url_params=%7B%3Aw%3D%3E128%2C%20%3Ah%3D%3E128%2C%20%3Afit%3D%3E%22crop%22%2C%20%3Aauto%3D%3E%22format%22%7D"
  },
  {
    "title": "Staff Product Designer, Credit Karma",
    "name": "Nabil Kazerouni",
    "username": "@nabil",
    "interests": ["Mentoring", "Speaking on podcasts", "Volunteering"],
    "img": "https://polywork-production.imgix.net/122bcjs8to0qfzoo52sg6yntvaf3?ixlib=rails-4.2.0&url_params=%7B%3Aw%3D%3E128%2C%20%3Ah%3D%3E128%2C%20%3Afit%3D%3E%22crop%22%2C%20%3Aauto%3D%3E%22format%22%7D"
  },
  {
    "title": "Senior Software Engineer, Klarna",
    "name": "Marco Denisi",
    "username": "@marco35",
    "interests": ["Open Source Contributions", "Volunteering", "Participating in User Research"],
    "img": "https://polywork-production.imgix.net/rss4cw7iaeeo1ny2u5a5eleso9vb?ixlib=rails-4.2.0&url_params=%7B%3Aw%3D%3E128%2C%20%3Ah%3D%3E128%2C%20%3Afit%3D%3E%22crop%22%2C%20%3Aauto%3D%3E%22format%22%7D"
  },
  {
    "title": "Sr. Program Manager, Instacart",
    "name": "Anna Valenza",
    "username": "@annavalenza",
    "interests": ["Participating in User Research", "Full time roles", "Mentoring"],
    "img": "https://polywork-production.imgix.net/cdgq8n2ntiyp1k29ohfiq49q26qk?ixlib=rails-4.2.0&url_params=%7B%3Aw%3D%3E128%2C%20%3Ah%3D%3E128%2C%20%3Afit%3D%3E%22crop%22%2C%20%3Aauto%3D%3E%22format%22%7D"
  },
  {
    "title": "Developer Advocate, Magic",
    "name": "Mohammad Shahbaz Alam\n\n\n",
    "username": "@shahbaz",
    "interests": ["Giving resume feedback", "Mentoring", "Guest lecturing"],
    "img": "https://polywork-production.imgix.net/vt0whckyz3snksg2hm784jywrhkj?ixlib=rails-4.2.0&url_params=%7B%3Aw%3D%3E128%2C%20%3Ah%3D%3E128%2C%20%3Afit%3D%3E%22crop%22%2C%20%3Aauto%3D%3E%22format%22%7D"
  },
  {
    "title": "Senior Software Engineer, Netflix",
    "name": "Adam Miller",
    "username": "@adammiller",
    "interests": ["Open Source Contributions", "Mentoring", "Writing"],
    "img": "https://polywork-production.imgix.net/qj2r8u7clj5xd66ib7494gu8q9sk?ixlib=rails-4.2.0&url_params=%7B%3Aw%3D%3E128%2C%20%3Ah%3D%3E128%2C%20%3Afit%3D%3E%22crop%22%2C%20%3Aauto%3D%3E%22format%22%7D"
  },
  {
    "title": "Engineering Manager, Stripe",
    "name": "Jeremy Cutler",
    "username": "@cutlerish",
    "interests": ["Participating in User Research", "Activism", "Joining company boards"],
    "img": "https://polywork-production.imgix.net/spoq3evqjd5kk0l6dbrrtxhvrspa?ixlib=rails-4.2.0&url_params=%7B%3Aw%3D%3E128%2C%20%3Ah%3D%3E128%2C%20%3Afit%3D%3E%22crop%22%2C%20%3Aauto%3D%3E%22format%22%7D"
  },
  {
    "title": "Product, Coinbase",
    "name": "Muneeb Imtiaz",
    "username": "@immuneeb",
    "interests": ["Partnering on Side Projects", "Investing", "Participating in User Research"],
    "img": "https://polywork-production.imgix.net/u67rvm05ynrze5izrf0jgqp6l0ff?ixlib=rails-4.2.0&url_params=%7B%3Aw%3D%3E128%2C%20%3Ah%3D%3E128%2C%20%3Afit%3D%3E%22crop%22%2C%20%3Aauto%3D%3E%22format%22%7D"
  },
  {
    "title": "Director, Product, Snap Inc",
    "name": "Will Wu",
    "username": "@willwu",
    "interests": ["Advising companies"],
    "img": "https://polywork-production.imgix.net/yj4pt20mnj5061s2wa2edefrm3ju?ixlib=rails-4.2.0&url_params=%7B%3Aw%3D%3E128%2C%20%3Ah%3D%3E128%2C%20%3Afit%3D%3E%22crop%22%2C%20%3Aauto%3D%3E%22format%22%7D"
  },
  {
    "title": "Engineering Manager, Adobe Inc.",
    "name": "David Thomson",
    "username": "@dwlt",
    "interests": ["Beta testing new products", "Speaking at Events", "Writing"],
    "img": "https://polywork-production.imgix.net/adhyb8wljoago6ln55o3yppar5d8?ixlib=rails-4.2.0&url_params=%7B%3Aw%3D%3E128%2C%20%3Ah%3D%3E128%2C%20%3Afit%3D%3E%22crop%22%2C%20%3Aauto%3D%3E%22format%22%7D"
  },
  {
    "title": "Software Engineer, Dropbox",
    "name": "Will Hodges",
    "username": "@wch",
    "interests": ["Mentoring", "Investing"],
    "img": "https://polywork-production.imgix.net/u5w1oe7id01n1uv4f0kqvfu1b7q6?ixlib=rails-4.2.0&url_params=%7B%3Aw%3D%3E128%2C%20%3Ah%3D%3E128%2C%20%3Afit%3D%3E%22crop%22%2C%20%3Aauto%3D%3E%22format%22%7D"
  },
  {
    "title": "Manager, Coinbase",
    "name": "Patrick McKinney",
    "username": "@pmckinney",
    "interests": ["Partnering on Side Projects", "Volunteering", "Joining company boards"],
    "img": "https://polywork-production.imgix.net/e1xxe1i9t14r08vxw2dpe2yu46j0?ixlib=rails-4.2.0&url_params=%7B%3Aw%3D%3E128%2C%20%3Ah%3D%3E128%2C%20%3Afit%3D%3E%22crop%22%2C%20%3Aauto%3D%3E%22format%22%7D"
  },
  {
    "title": "Senior Director of Product Management, GitHub",
    "name": "Julian Dunn\n\n\n",
    "username": "@jdunn",
    "interests": ["Advising companies", "Mentoring", "Brainstorming"],
    "img": "https://polywork-production.imgix.net/fmtebm71wz47nbj0p71nxdl0ecgf?ixlib=rails-4.2.0&url_params=%7B%3Aw%3D%3E128%2C%20%3Ah%3D%3E128%2C%20%3Afit%3D%3E%22crop%22%2C%20%3Aauto%3D%3E%22format%22%7D"
  },
  {
    "title": "Founder, Worklife Ventures",
    "name": "Bri Kimmel\n\n\n",
    "username": "@brianne",
    "interests": ["Speaking on Clubhouse", "Investing", "Speaking on podcasts"],
    "img": "https://polywork-production.imgix.net/x27xln59dzfumdke64uw16e31sud?ixlib=rails-4.2.0&url_params=%7B%3Aw%3D%3E128%2C%20%3Ah%3D%3E128%2C%20%3Afit%3D%3E%22crop%22%2C%20%3Aauto%3D%3E%22format%22%7D"
  },
  {
    "title": "Fashion Model, Freelance Model",
    "name": "Jessica Yang\n\n\n",
    "username": "@jesych",
    "interests": ["Mentoring", "Content Creation", "Speaking on podcasts"],
    "img": "https://polywork-production.imgix.net/pnviavkw2x4by5p75w5cgjc9vug0?ixlib=rails-4.2.0&url_params=%7B%3Aw%3D%3E128%2C%20%3Ah%3D%3E128%2C%20%3Afit%3D%3E%22crop%22%2C%20%3Aauto%3D%3E%22format%22%7D"
  },
  {
    "title": "Developer Advocate, Stripe",
    "name": "Mike Bifulco\n\n\n",
    "username": "@irreverentmike",
    "interests": ["Open Source Contributions", "Investing", "Guest lecturing"],
    "img": "https://polywork-production.imgix.net/75qo6pgf0cho6fsehvpbj6ajatil?ixlib=rails-4.2.0&url_params=%7B%3Aw%3D%3E128%2C%20%3Ah%3D%3E128%2C%20%3Afit%3D%3E%22crop%22%2C%20%3Aauto%3D%3E%22format%22%7D"
  },
  {
    "title": "Principal Engineer, Klarna",
    "name": "Tadeu Zagallo",
    "username": "@tadeuzagallo",
    "interests": ["Giving resume feedback", "Mentoring", "Speaking at Events"],
    "img": "https://polywork-production.imgix.net/hjjyc1fqsaxoor5okkttksljhed5?ixlib=rails-4.2.0&url_params=%7B%3Aw%3D%3E128%2C%20%3Ah%3D%3E128%2C%20%3Afit%3D%3E%22crop%22%2C%20%3Aauto%3D%3E%22format%22%7D"
  },
  {
    "title": "Staff Software Engineer, Airbnb",
    "name": "Matt Mulder",
    "username": "@mxmul",
    "interests": ["Beta testing new products", "Writing", "Open Source Contributions"],
    "img": "https://polywork-production.imgix.net/mu1ekuet3at9r925qhm6lb4kbg7j?ixlib=rails-4.2.0&url_params=%7B%3Aw%3D%3E128%2C%20%3Ah%3D%3E128%2C%20%3Afit%3D%3E%22crop%22%2C%20%3Aauto%3D%3E%22format%22%7D"
  },
  {
    "title": "Design Director & Principal Designer, Brex",
    "name": "Maykel Loomans",
    "username": "@maykel",
    "interests": ["Partnering on Side Projects", "Investing"],
    "img": "https://polywork-production.imgix.net/yndm8au7d9mjxyb1q1ruve3xlubu?ixlib=rails-4.2.0&url_params=%7B%3Aw%3D%3E128%2C%20%3Ah%3D%3E128%2C%20%3Afit%3D%3E%22crop%22%2C%20%3Aauto%3D%3E%22format%22%7D"
  },
  {
    "title": "Senior Software Engineer, Netflix",
    "name": "Laurie Barth",
    "username": "@laurieontech",
    "interests": ["Speaking on podcasts"],
    "img": "https://polywork-production.imgix.net/r9evfrmbtyd8vas8pexojjmwuhn6?ixlib=rails-4.2.0&url_params=%7B%3Aw%3D%3E128%2C%20%3Ah%3D%3E128%2C%20%3Afit%3D%3E%22crop%22%2C%20%3Aauto%3D%3E%22format%22%7D"
  },
  {
    "title": "Engineering Team Manager, Squarespace",
    "name": "Evan Smith",
    "username": "@thejokersthief",
    "interests": ["Giving resume feedback", "Guest lecturing", "Volunteering"],
    "img": "https://polywork-production.imgix.net/21o4le2i0udwsgvbwfbh57gt2rdn?ixlib=rails-4.2.0&url_params=%7B%3Aw%3D%3E128%2C%20%3Ah%3D%3E128%2C%20%3Afit%3D%3E%22crop%22%2C%20%3Aauto%3D%3E%22format%22%7D"
  },
  {
    "title": "Software Engineer, Netlify",
    "name": "Natalie Davis\n\n\n",
    "username": "@natalie",
    "interests": ["Mentoring", "Content Creation", "Speaking at Events"],
    "img": "https://polywork-production.imgix.net/rxwklg4lwc1bh0qjppqhhe140kqa?ixlib=rails-4.2.0&url_params=%7B%3Aw%3D%3E128%2C%20%3Ah%3D%3E128%2C%20%3Afit%3D%3E%22crop%22%2C%20%3Aauto%3D%3E%22format%22%7D"
  },
  {
    "title": "Diversity & Inclusion Lead, Talent Acquisition, Klarna",
    "name": "Marina Ivanović",
    "username": "@marinaivanovic",
    "interests": ["Guest lecturing", "Speaking on Clubhouse", "Activism"],
    "img": "https://polywork-production.imgix.net/p1z0q3hhtfit45fv2vd1596p10f4?ixlib=rails-4.2.0&url_params=%7B%3Aw%3D%3E128%2C%20%3Ah%3D%3E128%2C%20%3Afit%3D%3E%22crop%22%2C%20%3Aauto%3D%3E%22format%22%7D"
  },
  {
    "title": "Operating Partner, Seven Seven Six",
    "name": "Cristina Georgoulakis",
    "username": "@cristina_apple",
    "interests": ["Speaking on Clubhouse", "Speaking at Events", "Advising companies"],
    "img": "https://polywork-production.imgix.net/03ihh45ubkmirsy325425ak93h4b?ixlib=rails-4.2.0&url_params=%7B%3Aw%3D%3E128%2C%20%3Ah%3D%3E128%2C%20%3Afit%3D%3E%22crop%22%2C%20%3Aauto%3D%3E%22format%22%7D"
  },
  {
    "title": "Sr. Engineering Manager, Zapier",
    "name": "Scott Williams",
    "username": "@swilliams",
    "interests": ["Advising companies", "Speaking on podcasts"],
    "img": "https://polywork-production.imgix.net/7j3sxtio1p5e5f05i1yvesk0msxd?ixlib=rails-4.2.0&url_params=%7B%3Aw%3D%3E128%2C%20%3Ah%3D%3E128%2C%20%3Afit%3D%3E%22crop%22%2C%20%3Aauto%3D%3E%22format%22%7D"
  },
  {
    "title": "Senior Software Engineer, Uber",
    "name": "Jeff Chheng",
    "username": "@jeffchheng",
    "interests": ["Giving resume feedback", "Mentoring", "Writing"],
    "img": "https://polywork-production.imgix.net/ohmgen2midtme7w4bq7qwlw4m7ai?ixlib=rails-4.2.0&url_params=%7B%3Aw%3D%3E128%2C%20%3Ah%3D%3E128%2C%20%3Afit%3D%3E%22crop%22%2C%20%3Aauto%3D%3E%22format%22%7D"
  },
  {
    "title": "Dev. Relations Manager, Stack Overflow",
    "name": "Shodipo Ayomide",
    "username": "@developerayo",
    "interests": ["Open Source Contributions", "Guest lecturing", "Raising funding"],
    "img": "https://polywork-production.imgix.net/gerrk8bdhgdfjfwzn1nxq47hgi6a?ixlib=rails-4.2.0&url_params=%7B%3Aw%3D%3E128%2C%20%3Ah%3D%3E128%2C%20%3Afit%3D%3E%22crop%22%2C%20%3Aauto%3D%3E%22format%22%7D"
  },
  {
    "title": "Lead Product Evangelist, DocuSign",
    "name": "Jon Levesque",
    "username": "@jonjlevesque",
    "interests": ["Guest lecturing", "Beta testing new products", "Speaking at Events"],
    "img": "https://polywork-production.imgix.net/72pvjbjwceyn2mjbeiyrmrnypnxr?ixlib=rails-4.2.0&url_params=%7B%3Aw%3D%3E128%2C%20%3Ah%3D%3E128%2C%20%3Afit%3D%3E%22crop%22%2C%20%3Aauto%3D%3E%22format%22%7D"
  },
  {
    "title": "Senior Product Designer, Dropbox",
    "name": "Kris Puckett",
    "username": "@kris",
    "interests": ["Speaking on Clubhouse", "Giving resume feedback", "Mentoring"],
    "img": "https://polywork-production.imgix.net/d7v1sxgark75t19af0or7h2bdcli?ixlib=rails-4.2.0&url_params=%7B%3Aw%3D%3E128%2C%20%3Ah%3D%3E128%2C%20%3Afit%3D%3E%22crop%22%2C%20%3Aauto%3D%3E%22format%22%7D"
  },
  {
    "title": "Staff Product Designer, Coinbase",
    "name": "Chloe Park",
    "username": "@chloepark",
    "interests": ["Partnering on Side Projects", "Investing", "Live Streaming"],
    "img": "https://polywork-production.imgix.net/vn4hpibcgo90caiyxqp1uziuwujh?ixlib=rails-4.2.0&url_params=%7B%3Aw%3D%3E128%2C%20%3Ah%3D%3E128%2C%20%3Afit%3D%3E%22crop%22%2C%20%3Aauto%3D%3E%22format%22%7D"
  },
  {
    "title": "Senior Manager, Developer Community, HubSpot",
    "name": "Sarah-Jane Morris",
    "username": "@sarahjanemorris",
    "interests": ["Activism", "Speaking on podcasts"],
    "img": "https://polywork-production.imgix.net/3z0xhpfborbqxtvungo2ixuxdz70?ixlib=rails-4.2.0&url_params=%7B%3Aw%3D%3E128%2C%20%3Ah%3D%3E128%2C%20%3Afit%3D%3E%22crop%22%2C%20%3Aauto%3D%3E%22format%22%7D"
  },
  {
    "title": "Director of Developer Relations, New Relic",
    "name": "Jonan Scheffler",
    "username": "@thejonanshow",
    "interests": ["Mentoring", "Guest lecturing", "Investing"],
    "img": "https://polywork-production.imgix.net/0po8rfvu2uob1kfko2n9fbweq7ql?ixlib=rails-4.2.0&url_params=%7B%3Aw%3D%3E128%2C%20%3Ah%3D%3E128%2C%20%3Afit%3D%3E%22crop%22%2C%20%3Aauto%3D%3E%22format%22%7D"
  },
  {
    "title": "Strategic Partner Manager, Music Partnerships, Instagram",
    "name": "Tolu Ayeni",
    "username": "@tistolu",
    "interests": ["Partnering on Side Projects", "Joining company boards", "Mentoring"],
    "img": "https://polywork-production.imgix.net/4rwqz6a7pts3acswb3ln03ko8m6x?ixlib=rails-4.2.0&url_params=%7B%3Aw%3D%3E128%2C%20%3Ah%3D%3E128%2C%20%3Afit%3D%3E%22crop%22%2C%20%3Aauto%3D%3E%22format%22%7D"
  },
  {
    "title": "Creative A&R , Sony Music Publishing ",
    "name": "Rashad 📈🏁👾\n\n\n",
    "username": "@babyshad",
    "interests": ["Speaking on Clubhouse", "Content Creation", "Speaking at Events"],
    "img": "https://polywork-production.imgix.net/4ig9qorj5nusodwzqi7cxwjiy2sx?ixlib=rails-4.2.0&url_params=%7B%3Aw%3D%3E128%2C%20%3Ah%3D%3E128%2C%20%3Afit%3D%3E%22crop%22%2C%20%3Aauto%3D%3E%22format%22%7D"
  },
  {
    "title": "Software Engineer, Web, Uber",
    "name": "Joey Colon\n\n\n",
    "username": "@joey",
    "interests": ["Beta testing new products", "Participating in User Research", "Brainstorming"],
    "img": "https://polywork-production.imgix.net/zl0p4vb071gfejcrk2880t0xtkgx?ixlib=rails-4.2.0&url_params=%7B%3Aw%3D%3E128%2C%20%3Ah%3D%3E128%2C%20%3Afit%3D%3E%22crop%22%2C%20%3Aauto%3D%3E%22format%22%7D"
  },
  {
    "title": "Software Engineer, Apple Inc",
    "name": "Luke Burton",
    "username": "@hagmonk",
    "interests": ["Open Source Contributions", "Beta testing new products", "Mentoring"],
    "img": "https://polywork-production.imgix.net/4y8hb0zh8p3sn357bhcpybf65af6?ixlib=rails-4.2.0&url_params=%7B%3Aw%3D%3E128%2C%20%3Ah%3D%3E128%2C%20%3Afit%3D%3E%22crop%22%2C%20%3Aauto%3D%3E%22format%22%7D"
  },
  {
    "title": "Mentor, StartX",
    "name": "David Breger",
    "username": "@dbreger",
    "interests": ["Investing", "Speaking on Clubhouse", "Joining company boards"],
    "img": "https://polywork-production.imgix.net/9hu86smyyjhj6mny5s5ld0ri44rw?ixlib=rails-4.2.0&url_params=%7B%3Aw%3D%3E128%2C%20%3Ah%3D%3E128%2C%20%3Afit%3D%3E%22crop%22%2C%20%3Aauto%3D%3E%22format%22%7D"
  },
  {
    "title": "Head of Developer Experience and Education, Remote",
    "name": "Cassidy Williams\n\n\n",
    "username": "@cassidoo",
    "interests": ["Content Creation", "Advising companies", "Speaking on podcasts"],
    "img": "https://polywork-production.imgix.net/vkk45k95k61vit49nv7n2ojzzcbw?ixlib=rails-4.2.0&url_params=%7B%3Aw%3D%3E128%2C%20%3Ah%3D%3E128%2C%20%3Afit%3D%3E%22crop%22%2C%20%3Aauto%3D%3E%22format%22%7D"
  },
  {
    "title": "Product Marketing Director, Polywork",
    "name": "Hannah Copeland\n\n\n",
    "username": "@hannahcopeland",
    "interests": ["Mentoring", "Advising companies", "Speaking at Events"],
    "img": "https://polywork-production.imgix.net/t3mmfyg3bcs3r05ad14ae6btc4bl?ixlib=rails-4.2.0&url_params=%7B%3Aw%3D%3E128%2C%20%3Ah%3D%3E128%2C%20%3Afit%3D%3E%22crop%22%2C%20%3Aauto%3D%3E%22format%22%7D"
  },
  {
    "title": "Senior Software Engineer, Airbnb",
    "name": "Ian Remmel",
    "username": "@ianwremmel",
    "interests": ["Participating in User Research"],
    "img": "https://polywork-production.imgix.net/sq8o87ed7k5z4h0bymp2z5xq6b8y?ixlib=rails-4.2.0&url_params=%7B%3Aw%3D%3E128%2C%20%3Ah%3D%3E128%2C%20%3Afit%3D%3E%22crop%22%2C%20%3Aauto%3D%3E%22format%22%7D"
  },
  {
    "title": "Senior Community Engineer, Gitpod",
    "name": "Pauline P. Narvas\n\n\n",
    "username": "@pawlean",
    "interests": ["Live Streaming", "Speaking at Events", "Making Introductions"],
    "img": "https://polywork-production.imgix.net/x8k71dvqz6dem3lmfsniyqgcv2en?ixlib=rails-4.2.0&url_params=%7B%3Aw%3D%3E128%2C%20%3Ah%3D%3E128%2C%20%3Afit%3D%3E%22crop%22%2C%20%3Aauto%3D%3E%22format%22%7D"
  },
  {
    "title": "Staff Software Engineer, Netlify",
    "name": "Nick Taylor\n\n\n",
    "username": "@nickytonline",
    "interests": ["Speaking at Events", "Speaking on podcasts", "Live Streaming"],
    "img": "https://polywork-production.imgix.net/k8q07qck6546ffgvu5aurjbn8tsc?ixlib=rails-4.2.0&url_params=%7B%3Aw%3D%3E128%2C%20%3Ah%3D%3E128%2C%20%3Afit%3D%3E%22crop%22%2C%20%3Aauto%3D%3E%22format%22%7D"
  },
  {
    "title": "Developer Advocate, MuleSoft",
    "name": "Alex Martinez\n\n\n",
    "username": "@devalexmartinez",
    "interests": ["Mentoring", "Speaking at Events", "Writing"],
    "img": "https://polywork-production.imgix.net/62okra31tnzmof6rjhebkahtpzx3?ixlib=rails-4.2.0&url_params=%7B%3Aw%3D%3E128%2C%20%3Ah%3D%3E128%2C%20%3Afit%3D%3E%22crop%22%2C%20%3Aauto%3D%3E%22format%22%7D"
  },
  {
    "title": "Head of Typography, Adobe Inc.",
    "name": "Tim Brown\n\n\n",
    "username": "@timbrown",
    "interests": ["Speaking at Events", "Beta testing new products", "Advising companies"],
    "img": "https://polywork-production.imgix.net/a52c6n2xkq7gh4667xox8qekj9c8?ixlib=rails-4.2.0&url_params=%7B%3Aw%3D%3E128%2C%20%3Ah%3D%3E128%2C%20%3Afit%3D%3E%22crop%22%2C%20%3Aauto%3D%3E%22format%22%7D"
  },
  {
    "title": "Staff Developer Experience Engineer, Netlify",
    "name": "Salma Alam-Naylor\n\n\n",
    "username": "@whitep4nth3r",
    "interests": ["Mentoring", "Activism", "Content Creation"],
    "img": "https://polywork-production.imgix.net/9ybsq9w0l6co7xbzs1w7hyp2qytf?ixlib=rails-4.2.0&url_params=%7B%3Aw%3D%3E128%2C%20%3Ah%3D%3E128%2C%20%3Afit%3D%3E%22crop%22%2C%20%3Aauto%3D%3E%22format%22%7D"
  },
  {
    "title": "Software Engineer 3, PayPal",
    "name": "Anthony Miller",
    "username": "@amiller",
    "interests": ["Open Source Contributions", "Activism", "Writing"],
    "img": "https://polywork-production.imgix.net/w0i3g9ew8xhtf3fbr5q1dirh3dwa?ixlib=rails-4.2.0&url_params=%7B%3Aw%3D%3E128%2C%20%3Ah%3D%3E128%2C%20%3Afit%3D%3E%22crop%22%2C%20%3Aauto%3D%3E%22format%22%7D"
  },
  {
    "title": "Product Manager, Apple Inc",
    "name": "Justin Washington\n\n\n",
    "username": "@jaywash",
    "interests": ["Giving resume feedback", "Guest lecturing", "Mentoring"],
    "img": "https://polywork-production.imgix.net/cr7lui8513iwghlw9tl2gwh196hp?ixlib=rails-4.2.0&url_params=%7B%3Aw%3D%3E128%2C%20%3Ah%3D%3E128%2C%20%3Afit%3D%3E%22crop%22%2C%20%3Aauto%3D%3E%22format%22%7D"
  },
  {
    "title": "Product Director, Polywork",
    "name": "Matt Breuer\n\n\n",
    "username": "@mebreuer",
    "interests": ["Mentoring", "Investing", "Brainstorming"],
    "img": "https://polywork-production.imgix.net/9x8w3icxl3whmiqaacyrko41bhqu?ixlib=rails-4.2.0&url_params=%7B%3Aw%3D%3E128%2C%20%3Ah%3D%3E128%2C%20%3Afit%3D%3E%22crop%22%2C%20%3Aauto%3D%3E%22format%22%7D"
  },
  {
    "title": "Engineering Manager , WeWork",
    "name": "Brian Manley",
    "username": "@bmanley",
    "interests": ["Investing", "Live Streaming", "Giving resume feedback"],
    "img": "https://polywork-production.imgix.net/sckf7t1azt4zt69bp2udcsjle694?ixlib=rails-4.2.0&url_params=%7B%3Aw%3D%3E128%2C%20%3Ah%3D%3E128%2C%20%3Afit%3D%3E%22crop%22%2C%20%3Aauto%3D%3E%22format%22%7D"
  },
  {
    "title": "Group Product Manager, Intercom",
    "name": "Mathew Cropper\n\n\n",
    "username": "@mathewcropper",
    "interests": ["Giving resume feedback", "Mentoring", "Speaking at Events"],
    "img": "https://polywork-production.imgix.net/ff1kc6zgar6r0s4z5vz4c29kfpd3?ixlib=rails-4.2.0&url_params=%7B%3Aw%3D%3E128%2C%20%3Ah%3D%3E128%2C%20%3Afit%3D%3E%22crop%22%2C%20%3Aauto%3D%3E%22format%22%7D"
  },
  {
    "title": "Product Designer, Metalab",
    "name": "✨ Pg Gonni\n\n\n",
    "username": "@pg",
    "interests": ["Giving resume feedback", "Mentoring", "Content Creation"],
    "img": "https://polywork-production.imgix.net/x6zr7yvnqtr0zedk55cck66erok8?ixlib=rails-4.2.0&url_params=%7B%3Aw%3D%3E128%2C%20%3Ah%3D%3E128%2C%20%3Afit%3D%3E%22crop%22%2C%20%3Aauto%3D%3E%22format%22%7D"
  },
  {
    "title": "Head of People, Geneva",
    "name": "Sarah Park\n\n\n",
    "username": "@spark",
    "interests": ["Speaking at Events", "Advising companies", "Speaking on podcasts"],
    "img": "https://polywork-production.imgix.net/0kmha7eimnijmy3zsgu32hnoaize?ixlib=rails-4.2.0&url_params=%7B%3Aw%3D%3E128%2C%20%3Ah%3D%3E128%2C%20%3Afit%3D%3E%22crop%22%2C%20%3Aauto%3D%3E%22format%22%7D"
  },
  {
    "title": "Head of Operations and Partnerships, Audio, Medium",
    "name": "Ryan Duffy",
    "username": "@ryanduffy",
    "interests": ["Speaking on podcasts"],
    "img": "https://polywork-production.imgix.net/itbjlsb7vac9z66gq05zva1v3wt3?ixlib=rails-4.2.0&url_params=%7B%3Aw%3D%3E128%2C%20%3Ah%3D%3E128%2C%20%3Afit%3D%3E%22crop%22%2C%20%3Aauto%3D%3E%22format%22%7D"
  },
  {
    "title": "Senior Design Manager, Uber Eats",
    "name": "Chris Lee",
    "username": "@cleer",
    "interests": ["Speaking on Twitter Spaces", "Producing a Podcast", "Advising companies"],
    "img": "https://polywork-production.imgix.net/fs5r8wb1dbeuwi3fj38qv347nfwz?ixlib=rails-4.2.0&url_params=%7B%3Aw%3D%3E128%2C%20%3Ah%3D%3E128%2C%20%3Afit%3D%3E%22crop%22%2C%20%3Aauto%3D%3E%22format%22%7D"
  },
  {
    "title": "Design Director, Twitter",
    "name": "Jonas Downey\n\n\n",
    "username": "@jonasdowney",
    "interests": ["Mentoring", "Writing", "Advising companies"],
    "img": "https://polywork-production.imgix.net/hjoq7s6xjcozthgxsfryhubia057?ixlib=rails-4.2.0&url_params=%7B%3Aw%3D%3E128%2C%20%3Ah%3D%3E128%2C%20%3Afit%3D%3E%22crop%22%2C%20%3Aauto%3D%3E%22format%22%7D"
  },
  {
    "title": "Content Moderator, TikTok",
    "name": "William Dockery\n\n\n",
    "username": "@docks",
    "interests": ["Live Streaming", "Content Creation", "Brainstorming"],
    "img": "https://polywork-production.imgix.net/v2mfcxl86dmv2h2fggd3gxmwtraa?ixlib=rails-4.2.0&url_params=%7B%3Aw%3D%3E128%2C%20%3Ah%3D%3E128%2C%20%3Afit%3D%3E%22crop%22%2C%20%3Aauto%3D%3E%22format%22%7D"
  },
  {
    "title": "Senior Developer Advocate for JavaScript, Microsoft",
    "name": "Wassim Chegham\n\n\n",
    "username": "@wassimchegham",
    "interests": ["Open Source Contributions", "Mentoring", "Speaking at Events"],
    "img": "https://polywork-production.imgix.net/m0rnur7ohl7ahs542k41j2t7mtli?ixlib=rails-4.2.0&url_params=%7B%3Aw%3D%3E128%2C%20%3Ah%3D%3E128%2C%20%3Afit%3D%3E%22crop%22%2C%20%3Aauto%3D%3E%22format%22%7D"
  },
  {
    "title": "Design Advocacy, Figma",
    "name": "Clara Ujiie\n\n\n",
    "username": "@claraujiie",
    "interests": ["Speaking at Events", "Brainstorming", "Mentoring"],
    "img": "https://polywork-production.imgix.net/yxlesh232ecx6ha2wlmvas74ozyj?ixlib=rails-4.2.0&url_params=%7B%3Aw%3D%3E128%2C%20%3Ah%3D%3E128%2C%20%3Afit%3D%3E%22crop%22%2C%20%3Aauto%3D%3E%22format%22%7D"
  },
  {
    "title": "Engineering Manager, Square",
    "name": "Colin Curtin",
    "username": "@perplexes",
    "interests": ["Giving resume feedback", "Live Streaming", "Speaking on Clubhouse"],
    "img": "https://polywork-production.imgix.net/7hl72ti1wiryjcdoeobdnk3av2vr?ixlib=rails-4.2.0&url_params=%7B%3Aw%3D%3E128%2C%20%3Ah%3D%3E128%2C%20%3Afit%3D%3E%22crop%22%2C%20%3Aauto%3D%3E%22format%22%7D"
  },
  {
    "title": "DevOps Engineer, Dropbox",
    "name": "Jennifer Opal\n\n\n",
    "username": "@jenniferopal",
    "interests": ["Speaking at Events"],
    "img": "https://polywork-production.imgix.net/j7zz846df86osk4xku1iu04ptajh?ixlib=rails-4.2.0&url_params=%7B%3Aw%3D%3E128%2C%20%3Ah%3D%3E128%2C%20%3Afit%3D%3E%22crop%22%2C%20%3Aauto%3D%3E%22format%22%7D"
  },
  {
    "title": "Senior Technical Sourcer, Twitter",
    "name": "Brian Fink",
    "username": "@thebrianfink",
    "interests": ["Giving resume feedback", "Volunteering", "Live Streaming"],
    "img": "https://polywork-production.imgix.net/t6km5zpxnhduhqz6b5fcu2bxs7u5?ixlib=rails-4.2.0&url_params=%7B%3Aw%3D%3E128%2C%20%3Ah%3D%3E128%2C%20%3Afit%3D%3E%22crop%22%2C%20%3Aauto%3D%3E%22format%22%7D"
  },
  {
    "title": "Software Engineer II, Spotify",
    "name": "Ameera Al-shaibani",
    "username": "@ameera",
    "interests": ["Participating in User Research", "Open Source Contributions", "Giving resume feedback"],
    "img": "https://polywork-production.imgix.net/hxw2xxto61feyods06d5kuqkcuxx?ixlib=rails-4.2.0&url_params=%7B%3Aw%3D%3E128%2C%20%3Ah%3D%3E128%2C%20%3Afit%3D%3E%22crop%22%2C%20%3Aauto%3D%3E%22format%22%7D"
  },
  {
    "title": "Senior Operations Engineer, Duolingo",
    "name": "Ian Parker",
    "username": "@iwparker",
    "interests": ["Participating in User Research", "Open Source Contributions", "Giving resume feedback"],
    "img": "https://polywork-production.imgix.net/xciqxmr9fd8v51i8eidw2klhde90?ixlib=rails-4.2.0&url_params=%7B%3Aw%3D%3E128%2C%20%3Ah%3D%3E128%2C%20%3Afit%3D%3E%22crop%22%2C%20%3Aauto%3D%3E%22format%22%7D"
  },
  {
    "title": "Developer Relations Engineer, Google",
    "name": "Yuval Greenfield",
    "username": "@ubershmekel",
    "interests": ["Guest lecturing", "Live Streaming", "Speaking on Clubhouse"],
    "img": "https://polywork-production.imgix.net/56w8ycthi09wbth8vpfs4y5pfocn?ixlib=rails-4.2.0&url_params=%7B%3Aw%3D%3E128%2C%20%3Ah%3D%3E128%2C%20%3Afit%3D%3E%22crop%22%2C%20%3Aauto%3D%3E%22format%22%7D"
  },
  {
    "title": "Marketing Manager, Netlify",
    "name": "Lisa Kretsch",
    "username": "@lisakretsch",
    "interests": ["Participating in User Research", "Live Streaming", "Speaking on Clubhouse"],
    "img": "https://polywork-production.imgix.net/xzdo6r480q40e4hd7egth5a438n8?ixlib=rails-4.2.0&url_params=%7B%3Aw%3D%3E128%2C%20%3Ah%3D%3E128%2C%20%3Afit%3D%3E%22crop%22%2C%20%3Aauto%3D%3E%22format%22%7D"
  },
  {
    "title": "Senior Software Engineer, The New York Times",
    "name": "Jessie W",
    "username": "@jessiewuwu",
    "interests": ["Guest lecturing", "Giving resume feedback", "Volunteering"],
    "img": "https://polywork-production.imgix.net/bpspp1t5g8ow8u1aiso519dql6n1?ixlib=rails-4.2.0&url_params=%7B%3Aw%3D%3E128%2C%20%3Ah%3D%3E128%2C%20%3Afit%3D%3E%22crop%22%2C%20%3Aauto%3D%3E%22format%22%7D"
  },
  {
    "title": "Sr User Experience Designer II, Venmo",
    "name": "Peter Allen",
    "username": "@3fn",
    "interests": ["Guest lecturing", "Open Source Contributions", "Giving resume feedback"],
    "img": "https://polywork-production.imgix.net/l2rlovpzltch1jugvezk5s2ixzbd?ixlib=rails-4.2.0&url_params=%7B%3Aw%3D%3E128%2C%20%3Ah%3D%3E128%2C%20%3Afit%3D%3E%22crop%22%2C%20%3Aauto%3D%3E%22format%22%7D"
  },
  {
    "title": "Head of Design, MainStreet",
    "name": "Vlad Georgescu\n\n\n",
    "username": "@vlad",
    "interests": ["Speaking on Clubhouse", "Guest lecturing", "Beta testing new products"],
    "img": "https://polywork-production.imgix.net/d059mbq5ff077pjt284ndvqg9svp?ixlib=rails-4.2.0&url_params=%7B%3Aw%3D%3E128%2C%20%3Ah%3D%3E128%2C%20%3Afit%3D%3E%22crop%22%2C%20%3Aauto%3D%3E%22format%22%7D"
  },
  {
    "title": "Product Manager, Stripe",
    "name": "Dan Cobb",
    "username": "@dancobb",
    "interests": ["Participating in User Research", "Guest lecturing", "Advising companies"],
    "img": "https://polywork-production.imgix.net/chlnuusn8fyd191j076xqn1jqf6d?ixlib=rails-4.2.0&url_params=%7B%3Aw%3D%3E128%2C%20%3Ah%3D%3E128%2C%20%3Afit%3D%3E%22crop%22%2C%20%3Aauto%3D%3E%22format%22%7D"
  },
  {
    "title": "Fellow, On Deck",
    "name": "Albrey Brown\n\n\n",
    "username": "@albrey",
    "interests": ["Advising companies", "Investing", "Mentoring"],
    "img": "https://polywork-production.imgix.net/chb9ev8t6vsqvtb2ai3no3f14amm?ixlib=rails-4.2.0&url_params=%7B%3Aw%3D%3E128%2C%20%3Ah%3D%3E128%2C%20%3Afit%3D%3E%22crop%22%2C%20%3Aauto%3D%3E%22format%22%7D"
  },
  {
    "title": "Host, Learn With Jason",
    "name": "Jason Lengstorf\n\n\n",
    "username": "@jlengstorf",
    "interests": ["Content Creation", "Speaking at Events", "Writing"],
    "img": "https://polywork-production.imgix.net/qill7tyw3ezrqux18i94x1nmn7bo?ixlib=rails-4.2.0&url_params=%7B%3Aw%3D%3E128%2C%20%3Ah%3D%3E128%2C%20%3Afit%3D%3E%22crop%22%2C%20%3Aauto%3D%3E%22format%22%7D"
  },
  {
    "title": "Vice President, Lyft",
    "name": "Charles Stephens",
    "username": "@csteph01",
    "interests": ["Advising companies", "Full time roles", "Investing"],
    "img": "https://polywork-production.imgix.net/v8epwk1ozi2kmqewq6v7ok8qxl0y?ixlib=rails-4.2.0&url_params=%7B%3Aw%3D%3E128%2C%20%3Ah%3D%3E128%2C%20%3Afit%3D%3E%22crop%22%2C%20%3Aauto%3D%3E%22format%22%7D"
  },
  {
    "title": "Business Development, Dropbox",
    "name": "Alyssa Everson",
    "username": "@alyssac",
    "interests": ["Participating in User Research", "Guest lecturing", "Giving resume feedback"],
    "img": "https://polywork-production.imgix.net/h3faazhuvfnpcr4j5jbet468i7g9?ixlib=rails-4.2.0&url_params=%7B%3Aw%3D%3E128%2C%20%3Ah%3D%3E128%2C%20%3Afit%3D%3E%22crop%22%2C%20%3Aauto%3D%3E%22format%22%7D"
  },
  {
    "title": "Director, Product Design, HBO Max",
    "name": "Michael McWatters",
    "username": "@mmcwatters",
    "interests": ["Participating in User Research", "Giving resume feedback", "Speaking on Clubhouse"],
    "img": "https://polywork-production.imgix.net/eviyi86vralhprsucr4fosmu48mz?ixlib=rails-4.2.0&url_params=%7B%3Aw%3D%3E128%2C%20%3Ah%3D%3E128%2C%20%3Afit%3D%3E%22crop%22%2C%20%3Aauto%3D%3E%22format%22%7D"
  },
  {
    "title": "Senior Learning Consultant, Slack",
    "name": "Helena Nacinovic",
    "username": "@helenan",
    "interests": ["Participating in User Research", "Guest lecturing", "Open Source Contributions"],
    "img": "https://polywork-production.imgix.net/s4sboyzscc1ay6r7ti9ibs9soxyx?ixlib=rails-4.2.0&url_params=%7B%3Aw%3D%3E128%2C%20%3Ah%3D%3E128%2C%20%3Afit%3D%3E%22crop%22%2C%20%3Aauto%3D%3E%22format%22%7D"
  },
  {
    "title": "Staff Software Engineer, Slack",
    "name": "Mina Markham\n\n\n",
    "username": "@minamarkham",
    "interests": ["Guest lecturing", "Writing", "Making Introductions"],
    "img": "https://polywork-production.imgix.net/4violfsv2nxfnmihl50gt6bv2xdb?ixlib=rails-4.2.0&url_params=%7B%3Aw%3D%3E128%2C%20%3Ah%3D%3E128%2C%20%3Afit%3D%3E%22crop%22%2C%20%3Aauto%3D%3E%22format%22%7D"
  },
  {
    "title": "Product design lead, Google",
    "name": "Sri Jalasutram",
    "username": "@sridesign",
    "interests": ["Guest lecturing", "Making Introductions", "Advising companies"],
    "img": "https://polywork-production.imgix.net/7li0fwv2wv7543if79so327havue?ixlib=rails-4.2.0&url_params=%7B%3Aw%3D%3E128%2C%20%3Ah%3D%3E128%2C%20%3Afit%3D%3E%22crop%22%2C%20%3Aauto%3D%3E%22format%22%7D"
  }
]
